Workbook
Name Slicer_Clean_Status: #N/A
Name Slicer_Customer_City: #N/A
Name Slicer_Order_Month: #N/A
Name Slicer_Payment_Method: #N/A
Name Slicer_Restaurant_Name: #N/A

Sheet Row data wise pivote Analysis
B1: Order Status Analysis | F1: Operations Alert | J1: City-wise Orders | N1: Restaurant-wise Orders | R1: Restaurant Revenue | U1: Restaurant name wise net revenue | Y1: Operations Alert Pivot | AD1: Monthly Revenue
A3: Row Labels | B3: Count of Order_ID
A4: Cancelled | B4: 51 | E4: Row Labels | F4: Count of Operations_Alert | Q4: Row Labels | R4: Sum of Net_Revenue | U4: Row Labels | V4: Sum of Net_Revenue
A5: Delivered | B5: 215 | E5: Attention - Low Rating | F5: 39 | I5: Row Labels | J5: Count of Order_ID | Q5: Biryani House | R5: 16397.75 | U5: Pune Bites | V5: 24783.23 | Y5: Row Labels | Z5: Count of Order_ID
A6: Escalated | B6: 34 | E6: Critical - Cancelled | F6: 50 | I6: Bengaluru | J6: 50 | M6: Row Labels | N6: Count of Order_ID | Q6: Burger Garage | R6: 7748.96 | U6: Royal Thali | V6: 19227.23 | Y6: Attention - Low Rating | Z6: 39 | AC6: Row Labels | AD6: Sum of Net_Revenue
A7: Grand Total | B7: 300 | E7: Critical - Late Delivery | F7: 41 | I7: Hyderabad | J7: 38 | M7: Biryani House | N7: 14 | Q7: Cafe Aroma | R7: 13501.65 | U7: Tandoor Tales | V7: 18203.97 | Y7: Critical - Cancelled | Z7: 50 | AC7: May | AD7: 118074.57
E8: Normal | F8: 170 | I8: Mumbai | J8: 55 | M8: Burger Garage | N8: 8 | Q8: Chinese Wok | R8: 13620.22 | U8: Wok Express | V8: 18129.15 | Y8: Critical - Late Delivery | Z8: 41 | AC8: Jun | AD8: 112680.7
E9: Grand Total | F9: 300 | I9: Nagpur | J9: 55 | M9: Cafe Aroma | N9: 11 | Q9: Curry Leaf | R9: 14171.79 | U9: Dosa Junction | V9: 18059.57 | Y9: Normal | Z9: 170 | AC9: Jul | AD9: 115365.11
I10: Nashik | J10: 21 | M10: Chinese Wok | N10: 13 | Q10: Dosa Junction | R10: 18059.57 | U10: Spice Hub | V10: 17080.28 | Y10: Grand Total | Z10: 300 | AC10: Grand Total | AD10: 346120.38
I11: Pune | J11: 81 | M11: Curry Leaf | N11: 13 | Q11: Green Bowl | R11: 14766.23 | U11: Biryani House | V11: 16397.75
I12: Grand Total | J12: 300 | M12: Dosa Junction | N12: 14 | Q12: Grill House | R12: 15448.65 | U12: Grill House | V12: 15448.65
M13: Green Bowl | N13: 12 | Q13: Healthy Harvest | R13: 9914.63 | U13: Kebab Nation | V13: 15122.29
M14: Grill House | N14: 13 | Q14: Kebab Nation | R14: 15122.29 | U14: South Spice | V14: 14973.87
M15: Healthy Harvest | N15: 10 | Q15: Maharashtra Kitchen | R15: 10028.14 | U15: Green Bowl | V15: 14766.23
M16: Kebab Nation | N16: 15 | Q16: Mumbai Masala | R16: 9050.69 | U16: Pasta Point | V16: 14184.46
M17: Maharashtra Kitchen | N17: 10 | Q17: Pasta Point | R17: 14184.46 | U17: Curry Leaf | V17: 14171.79
M18: Mumbai Masala | N18: 8 | Q18: Pizza Craft | R18: 10240.29 | U18: Chinese Wok | V18: 13620.22
M19: Pasta Point | N19: 12 | Q19: Pune Bites | R19: 24783.23 | U19: Cafe Aroma | V19: 13501.65
M20: Pizza Craft | N20: 9 | Q20: Royal Thali | R20: 19227.23 | U20: Wrap Street | V20: 12037.7
M21: Pune Bites | N21: 20 | Q21: South Spice | R21: 14973.87 | U21: The Breakfast Club | V21: 11200.01
M22: Royal Thali | N22: 17 | Q22: Spice Hub | R22: 17080.28 | U22: Urban Tadka | V22: 10479.17
M23: South Spice | N23: 11 | Q23: Sweet Truth | R23: 10237.77 | U23: Pizza Craft | V23: 10240.29
M24: Spice Hub | N24: 17 | Q24: Tandoor Tales | R24: 18203.97 | U24: Sweet Truth | V24: 10237.77
... M30: Wok Express | N30: 16 | Q30: Grand Total | R30: 346120.38 | U30: Grand Total | V30: 346120.38
M31: Wrap Street | N31: 11
M32: Grand Total | N32: 300

Sheet Dashboard
I4: Total Revenue | K4: Total Orders | M4: Cancellation Rate | O4: Average Delivery Time | Q4: Average Customer Rating
I5: =SUM(Table1[Net_Revenue]) -> 346120.38 | K5: =COUNTA(Table1[Order_ID]) -> 300 | M5: =COUNTIF(Table1[Order_Status],"Cancelled")/COUNTA(Table1[Order_ID]) -> 0.16666667 | O5: =AVERAGE(Table1[Delivery_Time_Min]) -> 36.563333 | Q5: =AVERAGE(Table1[Customer_Rating]) -> 4.1471963

Sheet Raw_Orders
A1: Order_ID | B1: Order_Date | C1: Customer_ID | D1: Restaurant_ID | E1: Delivery_Partner_ID | F1: Order_Value | G1: Delivery_Fee | H1: Discount | I1: Distance_KM | J1: Delivery_Time_Min | K1: Customer_Rating | L1: Order_Status | M1: Clean_Status | N1: Payment_Method | O1: Clean_Payment_Method | P1: Coupon_Code | Q1: Clean_Coupon_Code | R1: Campaign_ID | S1: Cancellation_Reason | T1: Customer_Name | U1: Restaurant_Name | V1: Delivery_Partner_Name | W1: Campaign_Name | X1: Net_Revenue | Y1: Delivery SLA Status | Z1: Operations_Alert | AA1: Customer_City | AB1: Order_Month
A2: ORD00089 | B2: 46229 | C2: CUST060 | D2: REST005 | E2: DP012 | F2: 624.66 | G2: 35 | H2: 70.16 | I2: 6 | J2: 41 | K2: 4.5 | L2: CANCELLED | M2: =PROPER(TRIM(L2)) -> Cancelled | N2: Credit Card | O2: =TRIM(N2) -> Credit Card | P2: BUDGET50 | Q2: =TRIM(P2) -> BUDGET50 | R2: CMP003 | T2: =_xlfn.XLOOKUP(Table1[[#This Row],[Customer_ID]],Customers!A:A,Customers!B:B) -> Aditya Patil | U2: =_xlfn.XLOOKUP(Table1[[#This Row],[Restaurant_ID]],Restaurants!A:A,Restaurants!B:B) -> Green Bowl | V2: =_xlfn.XLOOKUP(Table1[[#This Row],[Delivery_Partner_ID]],Delivery_Partners!A:A,Delivery_Partners!B:B) -> Manoj | W2: =_xlfn.XLOOKUP(Table1[[#This Row],[Campaign_ID]],Campaigns!A:A,Campaigns!B:B) -> Premium Treat | X2: =Table1[[#This Row],[Order_Value]]+Table1[[#This Row],[Delivery_Fee]]-Table1[[#This Row],[Discount]] -> 589.5 | Y2: {=_xlfn.IFS(Table1[[#This Row],[Delivery_Time_Min]]<=30,"On Time",Table1[[#This Row],[Delivery_Time_Min]]<=45,"At Risk",TRUE,"SLA Breach")} -> At Risk | Z2: {=_xlfn.IFS( Table1[[#This Row],[Order_Status]]="Cancelled","Critical - Cancelled", Table1[[#This Row],[Delivery SLA Status]]="SLA Breach","Critical - Late Delivery", Table1[[#This Row],[Customer_Rating]]<3,"Attention - Low Rating", TRUE,"Normal" )} -> Normal | AA2: =_xlfn.XLOOKUP(Table1[[#This Row],[Customer_ID]],Customers!A:A,Customers!C:C) -> Nashik | AB2: =TEXT(Table1[[#This Row],[Order_Date]],"mmm") -> Jul
A3: ORD00008 | B3: 46158 | C3: CUST004 | D3: REST010 | E3: DP017 | F3: 1210.99 | G3: 35 | H3: 195.15 | I3: 4.8 | J3: 30 | L3: Cancelled | M3: =PROPER(TRIM(L3)) -> Cancelled | N3: Cash on Delivery | O3: =TRIM(N3) -> Cash on Delivery | P3: SAVE100 | Q3: =TRIM(P3) -> SAVE100 | R3: CMP002 | S3: Delivery partner unavailable | T3: =_xlfn.XLOOKUP(Table1[[#This Row],[Customer_ID]],Customers!A:A,Customers!B:B) -> Isha Pawar | U3: =_xlfn.XLOOKUP(Table1[[#This Row],[Restaurant_ID]],Restaurants!A:A,Restaurants!B:B) -> Dosa Junction | V3: =_xlfn.XLOOKUP(Table1[[#This Row],[Delivery_Partner_ID]],Delivery_Partners!A:A,Delivery_Partners!B:B) -> Sanjay | W3: =_xlfn.XLOOKUP(Table1[[#This Row],[Campaign_ID]],Campaigns!A:A,Campaigns!B:B) -> New User Boost | X3: =Table1[[#This Row],[Order_Value]]+Table1[[#This Row],[Delivery_Fee]]-Table1[[#This Row],[Discount]] -> 1050.84 | Y3: {=_xlfn.IFS(Table1[[#This Row],[Delivery_Time_Min]]<=30,"On Time",Table1[[#This Row],[Delivery_Time_Min]]<=45,"At Risk",TRUE,"SLA Breach")} -> On Time | Z3: {=_xlfn.IFS( Table1[[#This Row],[Order_Status]]="Cancelled","Critical - Cancelled", Table1[[#This Row],[Delivery SLA Status]]="SLA Breach","Critical - Late Delivery", Table1[[#This Row],[Customer_Rating]]<3,"Attention - Low Rating", TRUE,"Normal" )} -> Critical - Cancelled | AA3: =_xlfn.XLOOKUP(Table1[[#This Row],[Customer_ID]],Customers!A:A,Customers!C:C) -> Pune | AB3: =TEXT(Table1[[#This Row],[Order_Date]],"mmm") -> May
A4: ORD00011 | B4: 46149 | C4: CUST052 | D4: REST015 | E4: DP015 | F4: 1129.47 | G4: 30 | H4: 204.29 | I4: 1.7 | J4: 27 | L4: Cancelled | M4: =PROPER(TRIM(L4)) -> Cancelled | N4: Debit Card | O4: =TRIM(N4) -> Debit Card | P4: PREMIUM10 | Q4: =TRIM(P4) -> PREMIUM10 | R4: CMP007 | S4: Delivery partner unavailable | T4: =_xlfn.XLOOKUP(Table1[[#This Row],[Customer_ID]],Customers!A:A,Customers!B:B) -> Aarav Sharma | U4: =_xlfn.XLOOKUP(Table1[[#This Row],[Restaurant_ID]],Restaurants!A:A,Restaurants!B:B) -> Royal Thali | V4: =_xlfn.XLOOKUP(Table1[[#This Row],[Delivery_Partner_ID]],Delivery_Partners!A:A,Delivery_Partners!B:B) -> Vivek | W4: =_xlfn.XLOOKUP(Table1[[#This Row],[Campaign_ID]],Campaigns!A:A,Campaigns!B:B) -> First Order | X4: =Table1[[#This Row],[Order_Value]]+Table1[[#This Row],[Delivery_Fee]]-Table1[[#This Row],[Discount]] -> 955.18 | Y4: {=_xlfn.IFS(Table1[[#This Row],[Delivery_Time_Min]]<=30,"On Time",Table1[[#This Row],[Delivery_Time_Min]]<=45,"At Risk",TRUE,"SLA Breach")} -> On Time | Z4: {=_xlfn.IFS( Table1[[#This Row],[Order_Status]]="Cancelled","Critical - Cancelled", Table1[[#This Row],[Delivery SLA Status]]="SLA Breach","Critical - Late Delivery", Table1[[#This Row],[Customer_Rating]]<3,"Attention - Low Rating", TRUE,"Normal" )} -> Critical - Cancelled | AA4: =_xlfn.XLOOKUP(Table1[[#This Row],[Customer_ID]],Customers!A:A,Customers!C:C) -> Pune | AB4: =TEXT(Table1[[#This Row],[Order_Date]],"mmm") -> May
A5: ORD00014 | B5: 46145 | C5: CUST006 | D5: REST020 | E5: DP002 | F5: 609.25 | G5: 30 | H5: 69.72 | I5: 2.8 | J5: 33 | L5: Cancelled | M5: =PROPER(TRIM(L5)) -> Cancelled | N5: Wallet | O5: =TRIM(N5) -> Wallet | P5: SAVE100 | Q5: =TRIM(P5) -> SAVE100 | R5: CMP003 | S5: Restaurant delay | T5: =_xlfn.XLOOKUP(Table1[[#This Row],[Customer_ID]],Customers!A:A,Customers!B:B) -> Pooja Desai | U5: =_xlfn.XLOOKUP(Table1[[#This Row],[Restaurant_ID]],Restaurants!A:A,Restaurants!B:B) -> Wrap Street | V5: =_xlfn.XLOOKUP(Table1[[#This Row],[Delivery_Partner_ID]],Delivery_Partners!A:A,Delivery_Partners!B:B) -> Amit | W5: =_xlfn.XLOOKUP(Table1[[#This Row],[Campaign_ID]],Campaigns!A:A,Campaigns!B:B) -> Premium Treat | X5: =Table1[[#This Row],[Order_Value]]+Table1[[#This Row],[Delivery_Fee]]-Table1[[#This Row],[Discount]] -> 569.53 | Y5: {=_xlfn.IFS(Table1[[#This Row],[Delivery_Time_Min]]<=30,"On Time",Table1[[#This Row],[Delivery_Time_Min]]<=45,"At Risk",TRUE,"SLA Breach")} -> At Risk | Z5: {=_xlfn.IFS( Table1[[#This Row],[Order_Status]]="Cancelled","Critical - Cancelled", Table1[[#This Row],[Delivery SLA Status]]="SLA Breach","Critical - Late Delivery", Table1[[#This Row],[Customer_Rating]]<3,"Attention - Low Rating", TRUE,"Normal" )} -> Critical - Cancelled | AA5: =_xlfn.XLOOKUP(Table1[[#This Row],[Customer_ID]],Customers!A:A,Customers!C:C) -> Mumbai | AB5: =TEXT(Table1[[#This Row],[Order_Date]],"mmm") -> May
A6: ORD00024 | B6: 46231 | C6: CUST020 | D6: REST011 | E6: DP010 | F6: 509.41 | G6: 20 | H6: 0 | I6: 2.7 | J6: 39 | L6: Cancelled | M6: =PROPER(TRIM(L6)) -> Cancelled | N6: Cash on Delivery | O6: =TRIM(N6) -> Cash on Delivery | P6: NONE | Q6: =TRIM(P6) -> NONE | R6: CMP008 | S6: Customer changed mind | T6: =_xlfn.XLOOKUP(Table1[[#This Row],[Customer_ID]],Customers!A:A,Customers!B:B) -> Isha More | U6: =_xlfn.XLOOKUP(Table1[[#This Row],[Restaurant_ID]],Restaurants!A:A,Restaurants!B:B) -> Wok Express | V6: =_xlfn.XLOOKUP(Table1[[#This Row],[Delivery_Partner_ID]],Delivery_Partners!A:A,Delivery_Partners!B:B) -> Nitin | W6: =_xlfn.XLOOKUP(Table1[[#This Row],[Campaign_ID]],Campaigns!A:A,Campaigns!B:B) -> Monsoon Meals | X6: =Table1[[#This Row],[Order_Value]]+Table1[[#This Row],[Delivery_Fee]]-Table1[[#This Row],[Discount]] -> 529.41 | Y6: {=_xlfn.IFS(Table1[[#This Row],[Delivery_Time_Min]]<=30,"On Time",Table1[[#This Row],[Delivery_Time_Min]]<=45,"At Risk",TRUE,"SLA Breach")} -> At Risk | Z6: {=_xlfn.IFS( Table1[[#This Row],[Order_Status]]="Cancelled","Critical - Cancelled", Table1[[#This Row],[Delivery SLA Status]]="SLA Breach","Critical - Late Delivery", Table1[[#This Row],[Customer_Rating]]<3,"Attention - Low Rating", TRUE,"Normal" )} -> Critical - Cancelled | AA6: =_xlfn.XLOOKUP(Table1[[#This Row],[Customer_ID]],Customers!A:A,Customers!C:C) -> Pune | AB6: =TEXT(Table1[[#This Row],[Order_Date]],"mmm") -> Jul
A7: ORD00026 | B7: 46168 | C7: CUST054 | D7: REST023 | E7: DP001 | F7: 715.38 | G7: 20 | H7: 131.77 | I7: 3.3 | J7: 25 | L7: Cancelled | M7: =PROPER(TRIM(L7)) -> Cancelled | N7: Debit Card | O7: =TRIM(N7) -> Debit Card | P7: LUNCH15 | Q7: =TRIM(P7) -> LUNCH15 | R7: CMP007 | S7: Restaurant unavailable | T7: =_xlfn.XLOOKUP(Table1[[#This Row],[Customer_ID]],Customers!A:A,Customers!B:B) -> Nikhil Joshi | U7: =_xlfn.XLOOKUP(Table1[[#This Row],[Restaurant_ID]],Restaurants!A:A,Restaurants!B:B) -> Maharashtra Kitchen | V7: =_xlfn.XLOOKUP(Table1[[#This Row],[Delivery_Partner_ID]],Delivery_Partners!A:A,Delivery_Partners!B:B) -> Rahul | W7: =_xlfn.XLOOKUP(Table1[[#This Row],[Campaign_ID]],Campaigns!A:A,Campaigns!B:B) -> First Order | X7: =Table1[[#This Row],[Order_Value]]+Table1[[#This Row],[Delivery_Fee]]-Table1[[#This Row],[Discount]] -> 603.61 | Y7: {=_xlfn.IFS(Table1[[#This Row],[Delivery_Time_Min]]<=30,"On Time",Table1[[#This Row],[Delivery_Time_Min]]<=45,"At Risk",TRUE,"SLA Breach")} -> On Time | Z7: {=_xlfn.IFS( Table1[[#This Row],[Order_Status]]="Cancelled","Critical - Cancelled", Table1[[#This Row],[Delivery SLA Status]]="SLA Breach","Critical - Late Delivery", Table1[[#This Row],[Customer_Rating]]<3,"Attention - Low Rating", TRUE,"Normal" )} -> Critical - Cancelled | AA7: =_xlfn.XLOOKUP(Table1[[#This Row],[Customer_ID]],Customers!A:A,Customers!C:C) -> Nagpur | AB7: =TEXT(Table1[[#This Row],[Order_Date]],"mmm") -> May
A8: ORD00028 | B8: 46162 | C8: CUST070 | D8: REST021 | E8: DP001 | F8: 834.8 | G8: 50 | H8: 126.99 | I8: 11.7 | J8: 53 | L8: Cancelled | M8: =PROPER(TRIM(L8)) -> Cancelled | N8: Cash on Delivery | O8: =TRIM(N8) -> Cash on Delivery | P8: SAVE100 | Q8: =TRIM(P8) -> SAVE100 | R8: CMP001 | S8: Restaurant delay | T8: =_xlfn.XLOOKUP(Table1[[#This Row],[Customer_ID]],Customers!A:A,Customers!B:B) -> Sakshi Shinde | U8: =_xlfn.XLOOKUP(Table1[[#This Row],[Restaurant_ID]],Restaurants!A:A,Restaurants!B:B) -> Grill House | V8: =_xlfn.XLOOKUP(Table1[[#This Row],[Delivery_Partner_ID]],Delivery_Partners!A:A,Delivery_Partners!B:B) -> Rahul | W8: =_xlfn.XLOOKUP(Table1[[#This Row],[Campaign_ID]],Campaigns!A:A,Campaigns!B:B) -> Weekend Feast | X8: =Table1[[#This Row],[Order_Value]]+Table1[[#This Row],[Delivery_Fee]]-Table1[[#This Row],[Discount]] -> 757.81 | Y8: {=_xlfn.IFS(Table1[[#This Row],[Delivery_Time_Min]]<=30,"On Time",Table1[[#This Row],[Delivery_Time_Min]]<=45,"At Risk",TRUE,"SLA Breach")} -> SLA Breach | Z8: {=_xlfn.IFS( Table1[[#This Row],[Order_Status]]="Cancelled","Critical - Cancelled", Table1[[#This Row],[Delivery SLA Status]]="SLA Breach","Critical - Late Delivery", Table1[[#This Row],[Customer_Rating]]<3,"Attention - Low Rating", TRUE,"Normal" )} -> Critical - Cancelled | AA8: =_xlfn.XLOOKUP(Table1[[#This Row],[Customer_ID]],Customers!A:A,Customers!C:C) -> Hyderabad | AB8: =TEXT(Table1[[#This Row],[Order_Date]],"mmm") -> May
A9: ORD00030 | B9: 46197 | C9: CUST001 | D9: REST014 | E9: DP019 | F9: 2900.74 | G9: 60 | H9: 300 | I9: 2.1 | J9: 41 | L9: Cancelled | M9: =PROPER(TRIM(L9)) -> Cancelled | N9: Debit Card | O9: =TRIM(N9) -> Debit Card | P9: PREMIUM10 | Q9: =TRIM(P9) -> PREMIUM10 | R9: CMP007 | S9: Restaurant unavailable | T9: =_xlfn.XLOOKUP(Table1[[#This Row],[Customer_ID]],Customers!A:A,Customers!B:B) -> Neha Kulkarni | U9: =_xlfn.XLOOKUP(Table1[[#This Row],[Restaurant_ID]],Restaurants!A:A,Restaurants!B:B) -> Sweet Truth | V9: =_xlfn.XLOOKUP(Table1[[#This Row],[Delivery_Partner_ID]],Delivery_Partners!A:A,Delivery_Partners!B:B) -> Ajay | W9: =_xlfn.XLOOKUP(Table1[[#This Row],[Campaign_ID]],Campaigns!A:A,Campaigns!B:B) -> First Order | X9: =Table1[[#This Row],[Order_Value]]+Table1[[#This Row],[Delivery_Fee]]-Table1[[#This Row],[Discount]] -> 2660.74 | Y9: {=_xlfn.IFS(Table1[[#This Row],[Delivery_Time_Min]]<=30,"On Time",Table1[[#This Row],[Delivery_Time_Min]]<=45,"At Risk",TRUE,"SLA Breach")} -> At Risk | Z9: {=_xlfn.IFS( Table1[[#This Row],[Order_Status]]="Cancelled","Critical - Cancelled", Table1[[#This Row],[Delivery SLA Status]]="SLA Breach","Critical - Late Delivery", Table1[[#This Row],[Customer_Rating]]<3,"Attention - Low Rating", TRUE,"Normal" )} -> Critical - Cancelled | AA9: =_xlfn.XLOOKUP(Table1[[#This Row],[Customer_ID]],Customers!A:A,Customers!C:C) -> Nagpur | AB9: =TEXT(Table1[[#This Row],[Order_Date]],"mmm") -> Jun
A10: ORD00032 | B10: 46158 | C10: CUST072 | D10: REST022 | E10: DP015 | F10: 1414.16 | G10: 35 | H10: 161.28 | I10: 8.9 | J10: 34 | L10: Cancelled | M10: =PROPER(TRIM(L10)) -> Cancelled | N10: Cash on Delivery | O10: =TRIM(N10) -> Cash on Delivery | P10: WELCOME50 | Q10: =TRIM(P10) -> WELCOME50 | R10: CMP005 | S10: Delivery partner unavailable | T10: =_xlfn.XLOOKUP(Table1[[#This Row],[Customer_ID]],Customers!A:A,Customers!B:B) -> Sakshi Desai | U10: =_xlfn.XLOOKUP(Table1[[#This Row],[Restaurant_ID]],Restaurants!A:A,Restaurants!B:B) -> Chinese Wok | V10: =_xlfn.XLOOKUP(Table1[[#This Row],[Delivery_Partner_ID]],Delivery_Partners!A:A,Delivery_Partners!B:B) -> Vivek | W10: =_xlfn.XLOOKUP(Table1[[#This Row],[Campaign_ID]],Campaigns!A:A,Campaigns!B:B) -> Budget Bites | X10: =Table1[[#This Row],[Order_Value]]+Table1[[#This Row],[Delivery_Fee]]-Table1[[#This Row],[Discount]] -> 1287.88 | Y10: {=_xlfn.IFS(Table1[[#This Row],[Delivery_Time_Min]]<=30,"On Time",Table1[[#This Row],[Delivery_Time_Min]]<=45,"At Risk",TRUE,"SLA Breach")} -> At Risk | Z10: {=_xlfn.IFS( Table1[[#This Row],[Order_Status]]="Cancelled","Critical - Cancelled", Table1[[#This Row],[Delivery SLA Status]]="SLA Breach","Critical - Late Delivery", Table1[[#This Row],[Customer_Rating]]<3,"Attention - Low Rating", TRUE,"Normal" )} -> Critical - Cancelled | AA10: =_xlfn.XLOOKUP(Table1[[#This Row],[Customer_ID]],Customers!A:A,Customers!C:C) -> Hyderabad | AB10: =TEXT(Table1[[#This Row],[Order_Date]],"mmm") -> May
A11: ORD00034 | B11: 46195 | C11: CUST001 | D11: REST015 | E11: DP005 | F11: 1729.74 | G11: 35 | H11: 300 | I11: 4.8 | J11: 30 | L11: Cancelled | M11: =PROPER(TRIM(L11)) -> Cancelled | N11: Debit Card | O11: =TRIM(N11) -> Debit Card | P11: WELCOME50 | Q11: =TRIM(P11) -> WELCOME50 | R11: CMP004 | S11: Customer changed mind | T11: =_xlfn.XLOOKUP(Table1[[#This Row],[Customer_ID]],Customers!A:A,Customers!B:B) -> Neha Kulkarni | U11: =_xlfn.XLOOKUP(Table1[[#This Row],[Restaurant_ID]],Restaurants!A:A,Restaurants!B:B) -> Royal Thali | V11: =_xlfn.XLOOKUP(Table1[[#This Row],[Delivery_Partner_ID]],Delivery_Partners!A:A,Delivery_Partners!B:B) -> Ravi | W11: =_xlfn.XLOOKUP(Table1[[#This Row],[Campaign_ID]],Campaigns!A:A,Campaigns!B:B) -> Lunch Saver | X11: =Table1[[#This Row],[Order_Value]]+Table1[[#This Row],[Delivery_Fee]]-Table1[[#This Row],[Discount]] -> 1464.74 | Y11: {=_xlfn.IFS(Table1[[#This Row],[Delivery_Time_Min]]<=30,"On Time",Table1[[#This Row],[Delivery_Time_Min]]<=45,"At Risk",TRUE,"SLA Breach")} -> On Time | Z11: {=_xlfn.IFS( Table1[[#This Row],[Order_Status]]="Cancelled","Critical - Cancelled", Table1[[#This Row],[Delivery SLA Status]]="SLA Breach","Critical - Late Delivery", Table1[[#This Row],[Customer_Rating]]<3,"Attention - Low Rating", TRUE,"Normal" )} -> Critical - Cancelled | AA11: =_xlfn.XLOOKUP(Table1[[#This Row],[Customer_ID]],Customers!A:A,Customers!C:C) -> Nagpur | AB11: =TEXT(Table1[[#This Row],[Order_Date]],"mmm") -> Jun
A12: ORD00035 | B12: 46167 | C12: CUST024 | D12: REST017 | E12: DP010 | F12: 1707.44 | G12: 60 | H12: 141.97 | I12: 4 | J12: 31 | L12: Cancelled | M12: =PROPER(TRIM(L12)) -> Cancelled | N12: UPI | O12: =TRIM(N12) -> UPI | P12: LUNCH15 | Q12: =TRIM(P12) -> LUNCH15 | R12: CMP006 | S12: Customer changed mind | T12: =_xlfn.XLOOKUP(Table1[[#This Row],[Customer_ID]],Customers!A:A,Customers!B:B) -> Neha Kulkarni | U12: =_xlfn.XLOOKUP(Table1[[#This Row],[Restaurant_ID]],Restaurants!A:A,Restaurants!B:B) -> Kebab Nation | V12: =_xlfn.XLOOKUP(Table1[[#This Row],[Delivery_Partner_ID]],Delivery_Partners!A:A,Delivery_Partners!B:B) -> Nitin | W12: =_xlfn.XLOOKUP(Table1[[#This Row],[Campaign_ID]],Campaigns!A:A,Campaigns!B:B) -> Festival Special | X12: =Table1[[#This Row],[Order_Value]]+Table1[[#This Row],[Delivery_Fee]]-Table1[[#This Row],[Discount]] -> 1625.47 | Y12: {=_xlfn.IFS(Table1[[#This Row],[Delivery_Time_Min]]<=30,"On Time",Table1[[#This Row],[Delivery_Time_Min]]<=45,"At Risk",TRUE,"SLA Breach")} -> At Risk | Z12: {=_xlfn.IFS( Table1[[#This Row],[Order_Status]]="Cancelled","Critical - Cancelled", Table1[[#This Row],[Delivery SLA Status]]="SLA Breach","Critical - Late Delivery", Table1[[#This Row],[Customer_Rating]]<3,"Attention - Low Rating", TRUE,"Normal" )} -> Critical - Cancelled | AA12: =_xlfn.XLOOKUP(Table1[[#This Row],[Customer_ID]],Customers!A:A,Customers!C:C) -> Nagpur | AB12: =TEXT(Table1[[#This Row],[Order_Date]],"mmm") -> May
A13: ORD00050 | B13: 46210 | C13: CUST061 | D13: REST010 | E13: DP003 | F13: 1232.49 | G13: 50 | H13: 206.09 | I13: 9.2 | J13: 42 | L13: Cancelled | M13: =PROPER(TRIM(L13)) -> Cancelled | N13: Wallet | O13: =TRIM(N13) -> Wallet | P13: PREMIUM10 | Q13: =TRIM(P13) -> PREMIUM10 | R13: CMP002 | S13: Restaurant delay | T13: =_xlfn.XLOOKUP(Table1[[#This Row],[Customer_ID]],Customers!A:A,Customers!B:B) -> Neha Shinde | U13: =_xlfn.XLOOKUP(Table1[[#This Row],[Restaurant_ID]],Restaurants!A:A,Restaurants!B:B) -> Dosa Junction | V13: =_xlfn.XLOOKUP(Table1[[#This Row],[Delivery_Partner_ID]],Delivery_Partners!A:A,Delivery_Partners!B:B) -> Suresh | W13: =_xlfn.XLOOKUP(Table1[[#This Row],[Campaign_ID]],Campaigns!A:A,Campaigns!B:B) -> New User Boost | X13: =Table1[[#This Row],[Order_Value]]+Table1[[#This Row],[Delivery_Fee]]-Table1[[#This Row],[Discount]] -> 1076.4 | Y13: {=_xlfn.IFS(Table1[[#This Row],[Delivery_Time_Min]]<=30,"On Time",Table1[[#This Row],[Delivery_Time_Min]]<=45,"At Risk",TRUE,"SLA Breach")} -> At Risk | Z13: {=_xlfn.IFS( Table1[[#This Row],[Order_Status]]="Cancelled","Critical - Cancelled", Table1[[#This Row],[Delivery SLA Status]]="SLA Breach","Critical - Late Delivery", Table1[[#This Row],[Customer_Rating]]<3,"Attention - Low Rating", TRUE,"Normal" )} -> Critical - Cancelled | AA13: =_xlfn.XLOOKUP(Table1[[#This Row],[Customer_ID]],Customers!A:A,Customers!C:C) -> Bengaluru | AB13: =TEXT(Table1[[#This Row],[Order_Date]],"mmm") -> Jul
A14: ORD00051 | B14: 46147 | C14: CUST011 | D14: REST009 | E14: DP003 | F14: 1439.22 | G14: 25 | H14: 197.44 | I14: 5.1 | J14: 41 | L14: Cancelled | M14: =PROPER(TRIM(L14)) -> Cancelled | N14: Credit Card | O14: =TRIM(N14) -> Credit Card | P14: WELCOME50 | Q14: =TRIM(P14) -> WELCOME50 | R14: CMP003 | S14: Delivery partner unavailable | T14: =_xlfn.XLOOKUP(Table1[[#This Row],[Customer_ID]],Customers!A:A,Customers!B:B) -> Vivaan Pawar | U14: =_xlfn.XLOOKUP(Table1[[#This Row],[Restaurant_ID]],Restaurants!A:A,Restaurants!B:B) -> Cafe Aroma | V14: =_xlfn.XLOOKUP(Table1[[#This Row],[Delivery_Partner_ID]],Delivery_Partners!A:A,Delivery_Partners!B:B) -> Suresh | W14: =_xlfn.XLOOKUP(Table1[[#This Row],[Campaign_ID]],Campaigns!A:A,Campaigns!B:B) -> Premium Treat | X14: =Table1[[#This Row],[Order_Value]]+Table1[[#This Row],[Delivery_Fee]]-Table1[[#This Row],[Discount]] -> 1266.78 | Y14: {=_xlfn.IFS(Table1[[#This Row],[Delivery_Time_Min]]<=30,"On Time",Table1[[#This Row],[Delivery_Time_Min]]<=45,"At Risk",TRUE,"SLA Breach")} -> At Risk | Z14: {=_xlfn.IFS( Table1[[#This Row],[Order_Status]]="Cancelled","Critical - Cancelled", Table1[[#This Row],[Delivery SLA Status]]="SLA Breach","Critical - Late Delivery", Table1[[#This Row],[Customer_Rating]]<3,"Attention - Low Rating", TRUE,"Normal" )} -> Critical - Cancelled | AA14: =_xlfn.XLOOKUP(Table1[[#This Row],[Customer_ID]],Customers!A:A,Customers!C:C) -> Pune | AB14: =TEXT(Table1[[#This Row],[Order_Date]],"mmm") -> May
... A52: ORD00296 | B52: 46177 | C52: CUST050 | D52: REST006 | E52: DP020 | F52: 1212.54 | G52: 40 | H52: 124.62 | I52: 9.1 | J52: 57 | L52: Cancelled | M52: =PROPER(TRIM(L52)) -> Cancelled | N52: Debit Card | O52: =TRIM(N52) -> Debit Card | P52: LUNCH15 | Q52: =TRIM(P52) -> LUNCH15 | R52: CMP001 | S52: Restaurant unavailable | T52: =_xlfn.XLOOKUP(Table1[[#This Row],[Customer_ID]],Customers!A:A,Customers!B:B) -> Akash Pawar | U52: =_xlfn.XLOOKUP(Table1[[#This Row],[Restaurant_ID]],Restaurants!A:A,Restaurants!B:B) -> Mumbai Masala | V52: =_xlfn.XLOOKUP(Table1[[#This Row],[Delivery_Partner_ID]],Delivery_Partners!A:A,Delivery_Partners!B:B) -> Mahesh | W52: =_xlfn.XLOOKUP(Table1[[#This Row],[Campaign_ID]],Campaigns!A:A,Campaigns!B:B) -> Weekend Feast | X52: =Table1[[#This Row],[Order_Value]]+Table1[[#This Row],[Delivery_Fee]]-Table1[[#This Row],[Discount]] -> 1127.92 | Y52: {=_xlfn.IFS(Table1[[#This Row],[Delivery_Time_Min]]<=30,"On Time",Table1[[#This Row],[Delivery_Time_Min]]<=45,"At Risk",TRUE,"SLA Breach")} -> SLA Breach | Z52: {=_xlfn.IFS( Table1[[#This Row],[Order_Status]]="Cancelled","Critical - Cancelled", Table1[[#This Row],[Delivery SLA Status]]="SLA Breach","Critical - Late Delivery", Table1[[#This Row],[Customer_Rating]]<3,"Attention - Low Rating", TRUE,"Normal" )} -> Critical - Cancelled | AA52: =_xlfn.XLOOKUP(Table1[[#This Row],[Customer_ID]],Customers!A:A,Customers!C:C) -> Pune | AB52: =TEXT(Table1[[#This Row],[Order_Date]],"mmm") -> Jun
A53: ORD00001 | B53: 46170 | C53: CUST049 | D53: REST014 | E53: DP015 | F53: 2038.96 | G53: 40 | H53: 0 | I53: 1.6 | J53: 22 | K53: 4 | L53: Delivered | M53: =PROPER(TRIM(L53)) -> Delivered | N53: Credit Card | O53: =TRIM(N53) -> Credit Card | P53: NONE | Q53: =TRIM(P53) -> NONE | R53: CMP007 | T53: =_xlfn.XLOOKUP(Table1[[#This Row],[Customer_ID]],Customers!A:A,Customers!B:B) -> Priya Jadhav | U53: =_xlfn.XLOOKUP(Table1[[#This Row],[Restaurant_ID]],Restaurants!A:A,Restaurants!B:B) -> Sweet Truth | V53: =_xlfn.XLOOKUP(Table1[[#This Row],[Delivery_Partner_ID]],Delivery_Partners!A:A,Delivery_Partners!B:B) -> Vivek | W53: =_xlfn.XLOOKUP(Table1[[#This Row],[Campaign_ID]],Campaigns!A:A,Campaigns!B:B) -> First Order | X53: =Table1[[#This Row],[Order_Value]]+Table1[[#This Row],[Delivery_Fee]]-Table1[[#This Row],[Discount]] -> 2078.96 | Y53: {=_xlfn.IFS(Table1[[#This Row],[Delivery_Time_Min]]<=30,"On Time",Table1[[#This Row],[Delivery_Time_Min]]<=45,"At Risk",TRUE,"SLA Breach")} -> On Time | Z53: {=_xlfn.IFS( Table1[[#This Row],[Order_Status]]="Cancelled","Critical - Cancelled", Table1[[#This Row],[Delivery SLA Status]]="SLA Breach","Critical - Late Delivery", Table1[[#This Row],[Customer_Rating]]<3,"Attention - Low Rating", TRUE,"Normal" )} -> Normal | AA53: =_xlfn.XLOOKUP(Table1[[#This Row],[Customer_ID]],Customers!A:A,Customers!C:C) -> Hyderabad | AB53: =TEXT(Table1[[#This Row],[Order_Date]],"mmm") -> May
A54: ORD00002 | B54: 46211 | C54: CUST036 | D54: REST008 | E54: DP018 | F54: 478.31 | G54: 60 | H54: 49.15 | I54: 11 | J54: 48 | K54: 5 | L54: Delivered | M54: =PROPER(TRIM(L54)) -> Delivered | N54: UPI | O54: =TRIM(N54) -> UPI | P54: BUDGET50 | Q54: =TRIM(P54) -> BUDGET50 | R54: CMP004 | T54: =_xlfn.XLOOKUP(Table1[[#This Row],[Customer_ID]],Customers!A:A,Customers!B:B) -> Sakshi Sharma | U54: =_xlfn.XLOOKUP(Table1[[#This Row],[Restaurant_ID]],Restaurants!A:A,Restaurants!B:B) -> Biryani House | V54: =_xlfn.XLOOKUP(Table1[[#This Row],[Delivery_Partner_ID]],Delivery_Partners!A:A,Delivery_Partners!B:B) -> Anil | W54: =_xlfn.XLOOKUP(Table1[[#This Row],[Campaign_ID]],Campaigns!A:A,Campaigns!B:B) -> Lunch Saver | X54: =Table1[[#This Row],[Order_Value]]+Table1[[#This Row],[Delivery_Fee]]-Table1[[#This Row],[Discount]] -> 489.16 | Y54: {=_xlfn.IFS(Table1[[#This Row],[Delivery_Time_Min]]<=30,"On Time",Table1[[#This Row],[Delivery_Time_Min]]<=45,"At Risk",TRUE,"SLA Breach")} -> SLA Breach | Z54: {=_xlfn.IFS( Table1[[#This Row],[Order_Status]]="Cancelled","Critical - Cancelled", Table1[[#This Row],[Delivery SLA Status]]="SLA Breach","Critical - Late Delivery", Table1[[#This Row],[Customer_Rating]]<3,"Attention - Low Rating", TRUE,"Normal" )} -> Critical - Late Delivery | AA54: =_xlfn.XLOOKUP(Table1[[#This Row],[Customer_ID]],Customers!A:A,Customers!C:C) -> Pune | AB54: =TEXT(Table1[[#This Row],[Order_Date]],"mmm") -> Jul
A55: ORD00003 | B55: 46191 | C55: CUST066 | D55: REST010 | E55: DP018 | F55: 1850.12 | G55: 40 | H55: 300 | I55: 5.2 | J55: 31 | K55: 5 | L55: Delivered | M55: =PROPER(TRIM(L55)) -> Delivered | N55: UPI | O55: =TRIM(N55) -> UPI | P55: SAVE100 | Q55: =TRIM(P55) -> SAVE100 | R55: CMP003 | T55: =_xlfn.XLOOKUP(Table1[[#This Row],[Customer_ID]],Customers!A:A,Customers!B:B) -> Meera Desai | U55: =_xlfn.XLOOKUP(Table1[[#This Row],[Restaurant_ID]],Restaurants!A:A,Restaurants!B:B) -> Dosa Junction | V55: =_xlfn.XLOOKUP(Table1[[#This Row],[Delivery_Partner_ID]],Delivery_Partners!A:A,Delivery_Partners!B:B) -> Anil | W55: =_xlfn.XLOOKUP(Table1[[#This Row],[Campaign_ID]],Campaigns!A:A,Campaigns!B:B) -> Premium Treat | X55: =Table1[[#This Row],[Order_Value]]+Table1[[#This Row],[Delivery_Fee]]-Table1[[#This Row],[Discount]] -> 1590.12 | Y55: {=_xlfn.IFS(Table1[[#This Row],[Delivery_Time_Min]]<=30,"On Time",Table1[[#This Row],[Delivery_Time_Min]]<=45,"At Risk",TRUE,"SLA Breach")} -> At Risk | Z55: {=_xlfn.IFS( Table1[[#This Row],[Order_Status]]="Cancelled","Critical - Cancelled", Table1[[#This Row],[Delivery SLA Status]]="SLA Breach","Critical - Late Delivery", Table1[[#This Row],[Customer_Rating]]<3,"Attention - Low Rating", TRUE,"Normal" )} -> Normal | AA55: =_xlfn.XLOOKUP(Table1[[#This Row],[Customer_ID]],Customers!A:A,Customers!C:C) -> Bengaluru | AB55: =TEXT(Table1[[#This Row],[Order_Date]],"mmm") -> Jun
A56: ORD00004 | B56: 46216 | C56: CUST001 | D56: REST021 | E56: DP016 | F56: 1279.87 | G56: 25 | H56: 0 | I56: 7.1 | J56: 40 | K56: 4.5 | L56: Delivered | M56: =PROPER(TRIM(L56)) -> Delivered | N56: Debit Card | O56: =TRIM(N56) -> Debit Card | P56: NONE | Q56: =TRIM(P56) -> NONE | R56: CMP007 | T56: =_xlfn.XLOOKUP(Table1[[#This Row],[Customer_ID]],Customers!A:A,Customers!B:B) -> Neha Kulkarni | U56: =_xlfn.XLOOKUP(Table1[[#This Row],[Restaurant_ID]],Restaurants!A:A,Restaurants!B:B) -> Grill House | V56: =_xlfn.XLOOKUP(Table1[[#This Row],[Delivery_Partner_ID]],Delivery_Partners!A:A,Delivery_Partners!B:B) -> Rohit | W56: =_xlfn.XLOOKUP(Table1[[#This Row],[Campaign_ID]],Campaigns!A:A,Campaigns!B:B) -> First Order | X56: =Table1[[#This Row],[Order_Value]]+Table1[[#This Row],[Delivery_Fee]]-Table1[[#This Row],[Discount]] -> 1304.87 | Y56: {=_xlfn.IFS(Table1[[#This Row],[Delivery_Time_Min]]<=30,"On Time",Table1[[#This Row],[Delivery_Time_Min]]<=45,"At Risk",TRUE,"SLA Breach")} -> At Risk | Z56: {=_xlfn.IFS( Table1[[#This Row],[Order_Status]]="Cancelled","Critical - Cancelled", Table1[[#This Row],[Delivery SLA Status]]="SLA Breach","Critical - Late Delivery", Table1[[#This Row],[Customer_Rating]]<3,"Attention - Low Rating", TRUE,"Normal" )} -> Normal | AA56: =_xlfn.XLOOKUP(Table1[[#This Row],[Customer_ID]],Customers!A:A,Customers!C:C) -> Nagpur | AB56: =TEXT(Table1[[#This Row],[Order_Date]],"mmm") -> Jul
A57: ORD00006 | B57: 46206 | C57: CUST050 | D57: REST012 | E57: DP001 | F57: 1364.64 | G57: 35 | H57: 259.08 | I57: 8 | J57: 49 | K57: 5 | L57: Delivered | M57: =PROPER(TRIM(L57)) -> Delivered | N57: Credit Card | O57: =TRIM(N57) -> Credit Card | P57: LUNCH15 | Q57: =TRIM(P57) -> LUNCH15 | R57: CMP006 | T57: =_xlfn.XLOOKUP(Table1[[#This Row],[Customer_ID]],Customers!A:A,Customers!B:B) -> Akash Pawar | U57: =_xlfn.XLOOKUP(Table1[[#This Row],[Restaurant_ID]],Restaurants!A:A,Restaurants!B:B) -> Pizza Craft | V57: =_xlfn.XLOOKUP(Table1[[#This Row],[Delivery_Partner_ID]],Delivery_Partners!A:A,Delivery_Partners!B:B) -> Rahul | W57: =_xlfn.XLOOKUP(Table1[[#This Row],[Campaign_ID]],Campaigns!A:A,Campaigns!B:B) -> Festival Special | X57: =Table1[[#This Row],[Order_Value]]+Table1[[#This Row],[Delivery_Fee]]-Table1[[#This Row],[Discount]] -> 1140.56 | Y57: {=_xlfn.IFS(Table1[[#This Row],[Delivery_Time_Min]]<=30,"On Time",Table1[[#This Row],[Delivery_Time_Min]]<=45,"At Risk",TRUE,"SLA Breach")} -> SLA Breach | Z57: {=_xlfn.IFS( Table1[[#This Row],[Order_Status]]="Cancelled","Critical - Cancelled", Table1[[#This Row],[Delivery SLA Status]]="SLA Breach","Critical - Late Delivery", Table1[[#This Row],[Customer_Rating]]<3,"Attention - Low Rating", TRUE,"Normal" )} -> Critical - Late Delivery | AA57: =_xlfn.XLOOKUP(Table1[[#This Row],[Customer_ID]],Customers!A:A,Customers!C:C) -> Pune | AB57: =TEXT(Table1[[#This Row],[Order_Date]],"mmm") -> Jul
A58: ORD00007 | B58: 46223 | C58: CUST038 | D58: REST018 | E58: DP002 | F58: 673.86 | G58: 40 | H58: 102.4 | I58: 9.6 | J58: 28 | K58: 4.5 | L58: Delivered | M58: =PROPER(TRIM(L58)) -> Delivered | N58: Wallet | O58: =TRIM(N58) -> Wallet | P58: LUNCH15 | Q58: =TRIM(P58) -> LUNCH15 | R58: CMP002 | T58: =_xlfn.XLOOKUP(Table1[[#This Row],[Customer_ID]],Customers!A:A,Customers!B:B) -> Aditya Desai | U58: =_xlfn.XLOOKUP(Table1[[#This Row],[Restaurant_ID]],Restaurants!A:A,Restaurants!B:B) -> South Spice | V58: =_xlfn.XLOOKUP(Table1[[#This Row],[Delivery_Partner_ID]],Delivery_Partners!A:A,Delivery_Partners!B:B) -> Amit | W58: =_xlfn.XLOOKUP(Table1[[#This Row],[Campaign_ID]],Campaigns!A:A,Campaigns!B:B) -> New User Boost | X58: =Table1[[#This Row],[Order_Value]]+Table1[[#This Row],[Delivery_Fee]]-Table1[[#This Row],[Discount]] -> 611.46 | Y58: {=_xlfn.IFS(Table1[[#This Row],[Delivery_Time_Min]]<=30,"On Time",Table1[[#This Row],[Delivery_Time_Min]]<=45,"At Risk",TRUE,"SLA Breach")} -> On Time | Z58: {=_xlfn.IFS( Table1[[#This Row],[Order_Status]]="Cancelled","Critical - Cancelled", Table1[[#This Row],[Delivery SLA Status]]="SLA Breach","Critical - Late Delivery", Table1[[#This Row],[Customer_Rating]]<3,"Attention - Low Rating", TRUE,"Normal" )} -> Normal | AA58: =_xlfn.XLOOKUP(Table1[[#This Row],[Customer_ID]],Customers!A:A,Customers!C:C) -> Mumbai | AB58: =TEXT(Table1[[#This Row],[Order_Date]],"mmm") -> Jul
A59: ORD00010 | B59: 46143 | C59: CUST005 | D59: REST009 | E59: DP012 | F59: 662.87 | G59: 20 | H59: 116.86 | I59: 6.6 | J59: 29 | K59: 4 | L59: Delivered | M59: =PROPER(TRIM(L59)) -> Delivered | N59: Debit Card | O59: =TRIM(N59) -> Debit Card | P59: PREMIUM10 | Q59: =TRIM(P59) -> PREMIUM10 | R59: CMP002 | T59: =_xlfn.XLOOKUP(Table1[[#This Row],[Customer_ID]],Customers!A:A,Customers!B:B) -> Isha Gupta | U59: =_xlfn.XLOOKUP(Table1[[#This Row],[Restaurant_ID]],Restaurants!A:A,Restaurants!B:B) -> Cafe Aroma | V59: =_xlfn.XLOOKUP(Table1[[#This Row],[Delivery_Partner_ID]],Delivery_Partners!A:A,Delivery_Partners!B:B) -> Manoj | W59: =_xlfn.XLOOKUP(Table1[[#This Row],[Campaign_ID]],Campaigns!A:A,Campaigns!B:B) -> New User Boost | X59: =Table1[[#This Row],[Order_Value]]+Table1[[#This Row],[Delivery_Fee]]-Table1[[#This Row],[Discount]] -> 566.01 | Y59: {=_xlfn.IFS(Table1[[#This Row],[Delivery_Time_Min]]<=30,"On Time",Table1[[#This Row],[Delivery_Time_Min]]<=45,"At Risk",TRUE,"SLA Breach")} -> On Time | Z59: {=_xlfn.IFS( Table1[[#This Row],[Order_Status]]="Cancelled","Critical - Cancelled", Table1[[#This Row],[Delivery SLA Status]]="SLA Breach","Critical - Late Delivery", Table1[[#This Row],[Customer_Rating]]<3,"Attention - Low Rating", TRUE,"Normal" )} -> Normal | AA59: =_xlfn.XLOOKUP(Table1[[#This Row],[Customer_ID]],Customers!A:A,Customers!C:C) -> Bengaluru | AB59: =TEXT(Table1[[#This Row],[Order_Date]],"mmm") -> May
A60: ORD00013 | B60: 46184 | C60: CUST013 | D60: REST020 | E60: DP004 | F60: 1142.75 | G60: 20 | H60: 185.31 | I60: 9.2 | J60: 52 | K60: 4.5 | L60: Delivered | M60: =PROPER(TRIM(L60)) -> Delivered | N60: Wallet | O60: =TRIM(N60) -> Wallet | P60: PREMIUM10 | Q60: =TRIM(P60) -> PREMIUM10 | R60: CMP002 | T60: =_xlfn.XLOOKUP(Table1[[#This Row],[Customer_ID]],Customers!A:A,Customers!B:B) -> Sakshi More | U60: =_xlfn.XLOOKUP(Table1[[#This Row],[Restaurant_ID]],Restaurants!A:A,Restaurants!B:B) -> Wrap Street | V60: =_xlfn.XLOOKUP(Table1[[#This Row],[Delivery_Partner_ID]],Delivery_Partners!A:A,Delivery_Partners!B:B) -> Vikas | W60: =_xlfn.XLOOKUP(Table1[[#This Row],[Campaign_ID]],Campaigns!A:A,Campaigns!B:B) -> New User Boost | X60: =Table1[[#This Row],[Order_Value]]+Table1[[#This Row],[Delivery_Fee]]-Table1[[#This Row],[Discount]] -> 977.44 | Y60: {=_xlfn.IFS(Table1[[#This Row],[Delivery_Time_Min]]<=30,"On Time",Table1[[#This Row],[Delivery_Time_Min]]<=45,"At Risk",TRUE,"SLA Breach")} -> SLA Breach | Z60: {=_xlfn.IFS( Table1[[#This Row],[Order_Status]]="Cancelled","Critical - Cancelled", Table1[[#This Row],[Delivery SLA Status]]="SLA Breach","Critical - Late Delivery", Table1[[#This Row],[Customer_Rating]]<3,"Attention - Low Rating", TRUE,"Normal" )} -> Critical - Late Delivery | AA60: =_xlfn.XLOOKUP(Table1[[#This Row],[Customer_ID]],Customers!A:A,Customers!C:C) -> Bengaluru | AB60: =TEXT(Table1[[#This Row],[Order_Date]],"mmm") -> Jun
A61: ORD00015 | B61: 46199 | C61: CUST036 | D61: REST024 | E61: DP006 | F61: 1594.09 | G61: 25 | H61: 0 | I61: 6.4 | J61: 37 | K61: 4.5 | L61: Delivered | M61: =PROPER(TRIM(L61)) -> Delivered | N61: Debit Card | O61: =TRIM(N61) -> Debit Card | P61: NONE | Q61: =TRIM(P61) -> NONE | R61: CMP002 | T61: =_xlfn.XLOOKUP(Table1[[#This Row],[Customer_ID]],Customers!A:A,Customers!B:B) -> Sakshi Sharma | U61: =_xlfn.XLOOKUP(Table1[[#This Row],[Restaurant_ID]],Restaurants!A:A,Restaurants!B:B) -> Pasta Point | V61: =_xlfn.XLOOKUP(Table1[[#This Row],[Delivery_Partner_ID]],Delivery_Partners!A:A,Delivery_Partners!B:B) -> Kunal | W61: =_xlfn.XLOOKUP(Table1[[#This Row],[Campaign_ID]],Campaigns!A:A,Campaigns!B:B) -> New User Boost | X61: =Table1[[#This Row],[Order_Value]]+Table1[[#This Row],[Delivery_Fee]]-Table1[[#This Row],[Discount]] -> 1619.09 | Y61: {=_xlfn.IFS(Table1[[#This Row],[Delivery_Time_Min]]<=30,"On Time",Table1[[#This Row],[Delivery_Time_Min]]<=45,"At Risk",TRUE,"SLA Breach")} -> At Risk | Z61: {=_xlfn.IFS( Table1[[#This Row],[Order_Status]]="Cancelled","Critical - Cancelled", Table1[[#This Row],[Delivery SLA Status]]="SLA Breach","Critical - Late Delivery", Table1[[#This Row],[Customer_Rating]]<3,"Attention - Low Rating", TRUE,"Normal" )} -> Normal | AA61: =_xlfn.XLOOKUP(Table1[[#This Row],[Customer_ID]],Customers!A:A,Customers!C:C) -> Pune | AB61: =TEXT(Table1[[#This Row],[Order_Date]],"mmm") -> Jun
A62: ORD00016 | B62: 46153 | C62: CUST008 | D62: REST019 | E62: DP013 | F62: 764.88 | G62: 60 | H62: 136.92 | I62: 9.4 | J62: 47 | K62: 4.5 | L62: Delivered | M62: =PROPER(TRIM(L62)) -> Delivered | N62: Cash on Delivery | O62: =TRIM(N62) -> Cash on Delivery | P62: PREMIUM10 | Q62: =TRIM(P62) -> PREMIUM10 | R62: CMP004 | T62: =_xlfn.XLOOKUP(Table1[[#This Row],[Customer_ID]],Customers!A:A,Customers!B:B) -> Yash Kulkarni | U62: =_xlfn.XLOOKUP(Table1[[#This Row],[Restaurant_ID]],Restaurants!A:A,Restaurants!B:B) -> The Breakfast Club | V62: =_xlfn.XLOOKUP(Table1[[#This Row],[Delivery_Partner_ID]],Delivery_Partners!A:A,Delivery_Partners!B:B) -> Deepak | W62: =_xlfn.XLOOKUP(Table1[[#This Row],[Campaign_ID]],Campaigns!A:A,Campaigns!B:B) -> Lunch Saver | X62: =Table1[[#This Row],[Order_Value]]+Table1[[#This Row],[Delivery_Fee]]-Table1[[#This Row],[Discount]] -> 687.96 | Y62: {=_xlfn.IFS(Table1[[#This Row],[Delivery_Time_Min]]<=30,"On Time",Table1[[#This Row],[Delivery_Time_Min]]<=45,"At Risk",TRUE,"SLA Breach")} -> SLA Breach | Z62: {=_xlfn.IFS( Table1[[#This Row],[Order_Status]]="Cancelled","Critical - Cancelled", Table1[[#This Row],[Delivery SLA Status]]="SLA Breach","Critical - Late Delivery", Table1[[#This Row],[Customer_Rating]]<3,"Attention - Low Rating", TRUE,"Normal" )} -> Critical - Late Delivery | AA62: =_xlfn.XLOOKUP(Table1[[#This Row],[Customer_ID]],Customers!A:A,Customers!C:C) -> Nagpur | AB62: =TEXT(Table1[[#This Row],[Order_Date]],"mmm") -> May
A63: ORD00017 | B63: 46215 | C63: CUST077 | D63: REST011 | E63: DP003 | F63: 823.62 | G63: 20 | H63: 89.15 | I63: 8.5 | J63: 26 | K63: 4 | L63: Delivered | M63: =PROPER(TRIM(L63)) -> Delivered | N63: UPI | O63: =TRIM(N63) -> UPI | P63: PREMIUM10 | Q63: =TRIM(P63) -> PREMIUM10 | R63: CMP001 | T63: =_xlfn.XLOOKUP(Table1[[#This Row],[Customer_ID]],Customers!A:A,Customers!B:B) -> Aarav More | U63: =_xlfn.XLOOKUP(Table1[[#This Row],[Restaurant_ID]],Restaurants!A:A,Restaurants!B:B) -> Wok Express | V63: =_xlfn.XLOOKUP(Table1[[#This Row],[Delivery_Partner_ID]],Delivery_Partners!A:A,Delivery_Partners!B:B) -> Suresh | W63: =_xlfn.XLOOKUP(Table1[[#This Row],[Campaign_ID]],Campaigns!A:A,Campaigns!B:B) -> Weekend Feast | X63: =Table1[[#This Row],[Order_Value]]+Table1[[#This Row],[Delivery_Fee]]-Table1[[#This Row],[Discount]] -> 754.47 | Y63: {=_xlfn.IFS(Table1[[#This Row],[Delivery_Time_Min]]<=30,"On Time",Table1[[#This Row],[Delivery_Time_Min]]<=45,"At Risk",TRUE,"SLA Breach")} -> On Time | Z63: {=_xlfn.IFS( Table1[[#This Row],[Order_Status]]="Cancelled","Critical - Cancelled", Table1[[#This Row],[Delivery SLA Status]]="SLA Breach","Critical - Late Delivery", Table1[[#This Row],[Customer_Rating]]<3,"Attention - Low Rating", TRUE,"Normal" )} -> Normal | AA63: =_xlfn.XLOOKUP(Table1[[#This Row],[Customer_ID]],Customers!A:A,Customers!C:C) -> Bengaluru | AB63: =TEXT(Table1[[#This Row],[Order_Date]],"mmm") -> Jul
A64: ORD00018 | B64: 46218 | C64: CUST075 | D64: REST015 | E64: DP006 | F64: 1045.6 | G64: 30 | H64: 143.45 | I64: 11.3 | J64: 47 | L64: delivered | M64: =PROPER(TRIM(L64)) -> Delivered | N64: Debit Card | O64: =TRIM(N64) -> Debit Card | P64: MONSOON20 | Q64: =TRIM(P64) -> MONSOON20 | R64: CMP007 | S64: Customer changed mind | T64: =_xlfn.XLOOKUP(Table1[[#This Row],[Customer_ID]],Customers!A:A,Customers!B:B) -> Rahul Jadhav | U64: =_xlfn.XLOOKUP(Table1[[#This Row],[Restaurant_ID]],Restaurants!A:A,Restaurants!B:B) -> Royal Thali | V64: =_xlfn.XLOOKUP(Table1[[#This Row],[Delivery_Partner_ID]],Delivery_Partners!A:A,Delivery_Partners!B:B) -> Kunal | W64: =_xlfn.XLOOKUP(Table1[[#This Row],[Campaign_ID]],Campaigns!A:A,Campaigns!B:B) -> First Order | X64: =Table1[[#This Row],[Order_Value]]+Table1[[#This Row],[Delivery_Fee]]-Table1[[#This Row],[Discount]] -> 932.15 | Y64: {=_xlfn.IFS(Table1[[#This Row],[Delivery_Time_Min]]<=30,"On Time",Table1[[#This Row],[Delivery_Time_Min]]<=45,"At Risk",TRUE,"SLA Breach")} -> SLA Breach | Z64: {=_xlfn.IFS( Table1[[#This Row],[Order_Status]]="Cancelled","Critical - Cancelled", Table1[[#This Row],[Delivery SLA Status]]="SLA Breach","Critical - Late Delivery", Table1[[#This Row],[Customer_Rating]]<3,"Attention - Low Rating", TRUE,"Normal" )} -> Critical - Late Delivery | AA64: =_xlfn.XLOOKUP(Table1[[#This Row],[Customer_ID]],Customers!A:A,Customers!C:C) -> Pune | AB64: =TEXT(Table1[[#This Row],[Order_Date]],"mmm") -> Jul
A65: ORD00020 | B65: 46208 | C65: CUST042 | D65: REST025 | E65: DP018 | F65: 2305.95 | G65: 50 | H65: 300 | I65: 5.8 | J65: 32 | K65: 3.5 | L65: Delivered | M65: =PROPER(TRIM(L65)) -> Delivered | N65: Wallet | O65: =TRIM(N65) -> Wallet | P65: FESTIVE25 | Q65: =TRIM(P65) -> FESTIVE25 | R65: CMP008 | T65: =_xlfn.XLOOKUP(Table1[[#This Row],[Customer_ID]],Customers!A:A,Customers!B:B) -> Aarav Joshi | U65: =_xlfn.XLOOKUP(Table1[[#This Row],[Restaurant_ID]],Restaurants!A:A,Restaurants!B:B) -> Tandoor Tales | V65: =_xlfn.XLOOKUP(Table1[[#This Row],[Delivery_Partner_ID]],Delivery_Partners!A:A,Delivery_Partners!B:B) -> Anil | W65: =_xlfn.XLOOKUP(Table1[[#This Row],[Campaign_ID]],Campaigns!A:A,Campaigns!B:B) -> Monsoon Meals | X65: =Table1[[#This Row],[Order_Value]]+Table1[[#This Row],[Delivery_Fee]]-Table1[[#This Row],[Discount]] -> 2055.95 | Y65: {=_xlfn.IFS(Table1[[#This Row],[Delivery_Time_Min]]<=30,"On Time",Table1[[#This Row],[Delivery_Time_Min]]<=45,"At Risk",TRUE,"SLA Breach")} -> At Risk | Z65: {=_xlfn.IFS( Table1[[#This Row],[Order_Status]]="Cancelled","Critical - Cancelled", Table1[[#This Row],[Delivery SLA Status]]="SLA Breach","Critical - Late Delivery", Table1[[#This Row],[Customer_Rating]]<3,"Attention - Low Rating", TRUE,"Normal" )} -> Normal | AA65: =_xlfn.XLOOKUP(Table1[[#This Row],[Customer_ID]],Customers!A:A,Customers!C:C) -> Nagpur | AB65: =TEXT(Table1[[#This Row],[Order_Date]],"mmm") -> Jul
A66: ORD00021 | B66: 46169 | C66: CUST051 | D66: REST007 | E66: DP019 | F66: 1230.17 | G66: 35 | H66: 235.16 | I66: 7.8 | J66: 43 | K66: 4.5 | L66: Delivered | M66: =PROPER(TRIM(L66)) -> Delivered | N66: Wallet | O66: =TRIM(N66) -> Wallet | P66: SAVE100 | Q66: =TRIM(P66) -> SAVE100 | R66: CMP006 | T66: =_xlfn.XLOOKUP(Table1[[#This Row],[Customer_ID]],Customers!A:A,Customers!B:B) -> Amit Desai | U66: =_xlfn.XLOOKUP(Table1[[#This Row],[Restaurant_ID]],Restaurants!A:A,Restaurants!B:B) -> Pune Bites | V66: =_xlfn.XLOOKUP(Table1[[#This Row],[Delivery_Partner_ID]],Delivery_Partners!A:A,Delivery_Partners!B:B) -> Ajay | W66: =_xlfn.XLOOKUP(Table1[[#This Row],[Campaign_ID]],Campaigns!A:A,Campaigns!B:B) -> Festival Special | X66: =Table1[[#This Row],[Order_Value]]+Table1[[#This Row],[Delivery_Fee]]-Table1[[#This Row],[Discount]] -> 1030.01 | Y66: {=_xlfn.IFS(Table1[[#This Row],[Delivery_Time_Min]]<=30,"On Time",Table1[[#This Row],[Delivery_Time_Min]]<=45,"At Risk",TRUE,"SLA Breach")} -> At Risk | Z66: {=_xlfn.IFS( Table1[[#This Row],[Order_Status]]="Cancelled","Critical - Cancelled", Table1[[#This Row],[Delivery SLA Status]]="SLA Breach","Critical - Late Delivery", Table1[[#This Row],[Customer_Rating]]<3,"Attention - Low Rating", TRUE,"Normal" )} -> Normal | AA66: =_xlfn.XLOOKUP(Table1[[#This Row],[Customer_ID]],Customers!A:A,Customers!C:C) -> Nagpur | AB66: =TEXT(Table1[[#This Row],[Order_Date]],"mmm") -> May
A67: ORD00022 | B67: 46155 | C67: CUST038 | D67: REST025 | E67: DP001 | F67: 1615.01 | G67: 60 | H67: 300 | I67: 10.6 | J67: 39 | K67: 3 | L67: Delivered | M67: =PROPER(TRIM(L67)) -> Delivered | N67: Cash on Delivery | O67: =TRIM(N67) -> Cash on Delivery | P67: FESTIVE25 | Q67: =TRIM(P67) -> FESTIVE25 | R67: CMP005 | T67: =_xlfn.XLOOKUP(Table1[[#This Row],[Customer_ID]],Customers!A:A,Customers!B:B) -> Aditya Desai | U67: =_xlfn.XLOOKUP(Table1[[#This Row],[Restaurant_ID]],Restaurants!A:A,Restaurants!B:B) -> Tandoor Tales | V67: =_xlfn.XLOOKUP(Table1[[#This Row],[Delivery_Partner_ID]],Delivery_Partners!A:A,Delivery_Partners!B:B) -> Rahul | W67: =_xlfn.XLOOKUP(Table1[[#This Row],[Campaign_ID]],Campaigns!A:A,Campaigns!B:B) -> Budget Bites | X67: =Table1[[#This Row],[Order_Value]]+Table1[[#This Row],[Delivery_Fee]]-Table1[[#This Row],[Discount]] -> 1375.01 | Y67: {=_xlfn.IFS(Table1[[#This Row],[Delivery_Time_Min]]<=30,"On Time",Table1[[#This Row],[Delivery_Time_Min]]<=45,"At Risk",TRUE,"SLA Breach")} -> At Risk | Z67: {=_xlfn.IFS( Table1[[#This Row],[Order_Status]]="Cancelled","Critical - Cancelled", Table1[[#This Row],[Delivery SLA Status]]="SLA Breach","Critical - Late Delivery", Table1[[#This Row],[Customer_Rating]]<3,"Attention - Low Rating", TRUE,"Normal" )} -> Normal | AA67: =_xlfn.XLOOKUP(Table1[[#This Row],[Customer_ID]],Customers!A:A,Customers!C:C) -> Mumbai | AB67: =TEXT(Table1[[#This Row],[Order_Date]],"mmm") -> May
A68: ORD00023 | B68: 46185 | C68: CUST052 | D68: REST024 | E68: DP015 | F68: 727.41 | G68: 30 | H68: 59.44 | I68: 7.6 | J68: 60 | K68: 4.5 | L68: Delivered | M68: =PROPER(TRIM(L68)) -> Delivered | N68: Wallet | O68: =TRIM(N68) -> Wallet | P68: MONSOON20 | Q68: =TRIM(P68) -> MONSOON20 | R68: CMP005 | T68: =_xlfn.XLOOKUP(Table1[[#This Row],[Customer_ID]],Customers!A:A,Customers!B:B) -> Aarav Sharma | U68: =_xlfn.XLOOKUP(Table1[[#This Row],[Restaurant_ID]],Restaurants!A:A,Restaurants!B:B) -> Pasta Point | V68: =_xlfn.XLOOKUP(Table1[[#This Row],[Delivery_Partner_ID]],Delivery_Partners!A:A,Delivery_Partners!B:B) -> Vivek | W68: =_xlfn.XLOOKUP(Table1[[#This Row],[Campaign_ID]],Campaigns!A:A,Campaigns!B:B) -> Budget Bites | X68: =Table1[[#This Row],[Order_Value]]+Table1[[#This Row],[Delivery_Fee]]-Table1[[#This Row],[Discount]] -> 697.97 | Y68: {=_xlfn.IFS(Table1[[#This Row],[Delivery_Time_Min]]<=30,"On Time",Table1[[#This Row],[Delivery_Time_Min]]<=45,"At Risk",TRUE,"SLA Breach")} -> SLA Breach | Z68: {=_xlfn.IFS( Table1[[#This Row],[Order_Status]]="Cancelled","Critical - Cancelled", Table1[[#This Row],[Delivery SLA Status]]="SLA Breach","Critical - Late Delivery", Table1[[#This Row],[Customer_Rating]]<3,"Attention - Low Rating", TRUE,"Normal" )} -> Critical - Late Delivery | AA68: =_xlfn.XLOOKUP(Table1[[#This Row],[Customer_ID]],Customers!A:A,Customers!C:C) -> Pune | AB68: =TEXT(Table1[[#This Row],[Order_Date]],"mmm") -> Jun
A69: ORD00025 | B69: 46163 | C69: CUST043 | D69: REST012 | E69: DP012 | F69: 879.64 | G69: 25 | H69: 83.21 | I69: 10.2 | J69: 53 | K69: 3.5 | L69: Delivered | M69: =PROPER(TRIM(L69)) -> Delivered | N69: Cash on Delivery | O69: =TRIM(N69) -> Cash on Delivery | P69: WELCOME50 | Q69: =TRIM(P69) -> WELCOME50 | R69: CMP004 | T69: =_xlfn.XLOOKUP(Table1[[#This Row],[Customer_ID]],Customers!A:A,Customers!B:B) -> Sneha Desai | U69: =_xlfn.XLOOKUP(Table1[[#This Row],[Restaurant_ID]],Restaurants!A:A,Restaurants!B:B) -> Pizza Craft | V69: =_xlfn.XLOOKUP(Table1[[#This Row],[Delivery_Partner_ID]],Delivery_Partners!A:A,Delivery_Partners!B:B) -> Manoj | W69: =_xlfn.XLOOKUP(Table1[[#This Row],[Campaign_ID]],Campaigns!A:A,Campaigns!B:B) -> Lunch Saver | X69: =Table1[[#This Row],[Order_Value]]+Table1[[#This Row],[Delivery_Fee]]-Table1[[#This Row],[Discount]] -> 821.43 | Y69: {=_xlfn.IFS(Table1[[#This Row],[Delivery_Time_Min]]<=30,"On Time",Table1[[#This Row],[Delivery_Time_Min]]<=45,"At Risk",TRUE,"SLA Breach")} -> SLA Breach | Z69: {=_xlfn.IFS( Table1[[#This Row],[Order_Status]]="Cancelled","Critical - Cancelled", Table1[[#This Row],[Delivery SLA Status]]="SLA Breach","Critical - Late Delivery", Table1[[#This Row],[Customer_Rating]]<3,"Attention - Low Rating", TRUE,"Normal" )} -> Critical - Late Delivery | AA69: =_xlfn.XLOOKUP(Table1[[#This Row],[Customer_ID]],Customers!A:A,Customers!C:C) -> Hyderabad | AB69: =TEXT(Table1[[#This Row],[Order_Date]],"mmm") -> May
A70: ORD00027 | B70: 46167 | C70: CUST063 | D70: REST020 | E70: DP011 | F70: 641.09 | G70: 60 | H70: 71.45 | I70: 6 | J70: 26 | K70: 4 | L70: Delivered | M70: =PROPER(TRIM(L70)) -> Delivered | N70: Cash on Delivery | O70: =TRIM(N70) -> Cash on Delivery | P70: LUNCH15 | Q70: =TRIM(P70) -> LUNCH15 | R70: CMP006 | T70: =_xlfn.XLOOKUP(Table1[[#This Row],[Customer_ID]],Customers!A:A,Customers!B:B) -> Tanvi Kulkarni | U70: =_xlfn.XLOOKUP(Table1[[#This Row],[Restaurant_ID]],Restaurants!A:A,Restaurants!B:B) -> Wrap Street | V70: =_xlfn.XLOOKUP(Table1[[#This Row],[Delivery_Partner_ID]],Delivery_Partners!A:A,Delivery_Partners!B:B) -> Prakash | W70: =_xlfn.XLOOKUP(Table1[[#This Row],[Campaign_ID]],Campaigns!A:A,Campaigns!B:B) -> Festival Special | X70: =Table1[[#This Row],[Order_Value]]+Table1[[#This Row],[Delivery_Fee]]-Table1[[#This Row],[Discount]] -> 629.64 | Y70: {=_xlfn.IFS(Table1[[#This Row],[Delivery_Time_Min]]<=30,"On Time",Table1[[#This Row],[Delivery_Time_Min]]<=45,"At Risk",TRUE,"SLA Breach")} -> On Time | Z70: {=_xlfn.IFS( Table1[[#This Row],[Order_Status]]="Cancelled","Critical - Cancelled", Table1[[#This Row],[Delivery SLA Status]]="SLA Breach","Critical - Late Delivery", Table1[[#This Row],[Customer_Rating]]<3,"Attention - Low Rating", TRUE,"Normal" )} -> Normal | AA70: =_xlfn.XLOOKUP(Table1[[#This Row],[Customer_ID]],Customers!A:A,Customers!C:C) -> Pune | AB70: =TEXT(Table1[[#This Row],[Order_Date]],"mmm") -> May
A71: ORD00029 | B71: 46172 | C71: CUST063 | D71: REST008 | E71: DP017 | F71: 850.37 | G71: 30 | H71: 174.94 | I71: 3.3 | J71: 31 | K71: 2.5 | L71: Delivered | M71: =PROPER(TRIM(L71)) -> Delivered | N71: Credit Card | O71: =TRIM(N71) -> Credit Card | P71: SAVE100 | Q71: =TRIM(P71) -> SAVE100 | R71: CMP007 | T71: =_xlfn.XLOOKUP(Table1[[#This Row],[Customer_ID]],Customers!A:A,Customers!B:B) -> Tanvi Kulkarni | U71: =_xlfn.XLOOKUP(Table1[[#This Row],[Restaurant_ID]],Restaurants!A:A,Restaurants!B:B) -> Biryani House | V71: =_xlfn.XLOOKUP(Table1[[#This Row],[Delivery_Partner_ID]],Delivery_Partners!A:A,Delivery_Partners!B:B) -> Sanjay | W71: =_xlfn.XLOOKUP(Table1[[#This Row],[Campaign_ID]],Campaigns!A:A,Campaigns!B:B) -> First Order | X71: =Table1[[#This Row],[Order_Value]]+Table1[[#This Row],[Delivery_Fee]]-Table1[[#This Row],[Discount]] -> 705.43 | Y71: {=_xlfn.IFS(Table1[[#This Row],[Delivery_Time_Min]]<=30,"On Time",Table1[[#This Row],[Delivery_Time_Min]]<=45,"At Risk",TRUE,"SLA Breach")} -> At Risk | Z71: {=_xlfn.IFS( Table1[[#This Row],[Order_Status]]="Cancelled","Critical - Cancelled", Table1[[#This Row],[Delivery SLA Status]]="SLA Breach","Critical - Late Delivery", Table1[[#This Row],[Customer_Rating]]<3,"Attention - Low Rating", TRUE,"Normal" )} -> Attention - Low Rating | AA71: =_xlfn.XLOOKUP(Table1[[#This Row],[Customer_ID]],Customers!A:A,Customers!C:C) -> Pune | AB71: =TEXT(Table1[[#This Row],[Order_Date]],"mmm") -> May
A72: ORD00031 | B72: 46209 | C72: CUST032 | D72: REST010 | E72: DP010 | F72: 697.04 | G72: 60 | H72: 125.63 | I72: 8.2 | J72: 52 | K72: 4.5 | L72: Delivered | M72: =PROPER(TRIM(L72)) -> Delivered | N72: Debit Card | O72: =TRIM(N72) -> Debit Card | P72: SAVE100 | Q72: =TRIM(P72) -> SAVE100 | R72: CMP003 | T72: =_xlfn.XLOOKUP(Table1[[#This Row],[Customer_ID]],Customers!A:A,Customers!B:B) -> Tanvi Patil | U72: =_xlfn.XLOOKUP(Table1[[#This Row],[Restaurant_ID]],Restaurants!A:A,Restaurants!B:B) -> Dosa Junction | V72: =_xlfn.XLOOKUP(Table1[[#This Row],[Delivery_Partner_ID]],Delivery_Partners!A:A,Delivery_Partners!B:B) -> Nitin | W72: =_xlfn.XLOOKUP(Table1[[#This Row],[Campaign_ID]],Campaigns!A:A,Campaigns!B:B) -> Premium Treat | X72: =Table1[[#This Row],[Order_Value]]+Table1[[#This Row],[Delivery_Fee]]-Table1[[#This Row],[Discount]] -> 631.41 | Y72: {=_xlfn.IFS(Table1[[#This Row],[Delivery_Time_Min]]<=30,"On Time",Table1[[#This Row],[Delivery_Time_Min]]<=45,"At Risk",TRUE,"SLA Breach")} -> SLA Breach | Z72: {=_xlfn.IFS( Table1[[#This Row],[Order_Status]]="Cancelled","Critical - Cancelled", Table1[[#This Row],[Delivery SLA Status]]="SLA Breach","Critical - Late Delivery", Table1[[#This Row],[Customer_Rating]]<3,"Attention - Low Rating", TRUE,"Normal" )} -> Critical - Late Delivery | AA72: =_xlfn.XLOOKUP(Table1[[#This Row],[Customer_ID]],Customers!A:A,Customers!C:C) -> Bengaluru | AB72: =TEXT(Table1[[#This Row],[Order_Date]],"mmm") -> Jul
A73: ORD00033 | B73: 46202 | C73: CUST037 | D73: REST022 | E73: DP014 | F73: 879.33 | G73: 25 | H73: 174.76 | I73: 2.4 | J73: 27 | K73: 4.5 | L73: Delivered | M73: =PROPER(TRIM(L73)) -> Delivered | N73: Credit Card | O73: =TRIM(N73) -> Credit Card | P73: MONSOON20 | Q73: =TRIM(P73) -> MONSOON20 | R73: CMP007 | T73: =_xlfn.XLOOKUP(Table1[[#This Row],[Customer_ID]],Customers!A:A,Customers!B:B) -> Aditya Kulkarni | U73: =_xlfn.XLOOKUP(Table1[[#This Row],[Restaurant_ID]],Restaurants!A:A,Restaurants!B:B) -> Chinese Wok | V73: =_xlfn.XLOOKUP(Table1[[#This Row],[Delivery_Partner_ID]],Delivery_Partners!A:A,Delivery_Partners!B:B) -> Arjun | W73: =_xlfn.XLOOKUP(Table1[[#This Row],[Campaign_ID]],Campaigns!A:A,Campaigns!B:B) -> First Order | X73: =Table1[[#This Row],[Order_Value]]+Table1[[#This Row],[Delivery_Fee]]-Table1[[#This Row],[Discount]] -> 729.57 | Y73: {=_xlfn.IFS(Table1[[#This Row],[Delivery_Time_Min]]<=30,"On Time",Table1[[#This Row],[Delivery_Time_Min]]<=45,"At Risk",TRUE,"SLA Breach")} -> On Time | Z73: {=_xlfn.IFS( Table1[[#This Row],[Order_Status]]="Cancelled","Critical - Cancelled", Table1[[#This Row],[Delivery SLA Status]]="SLA Breach","Critical - Late Delivery", Table1[[#This Row],[Customer_Rating]]<3,"Attention - Low Rating", TRUE,"Normal" )} -> Normal | AA73: =_xlfn.XLOOKUP(Table1[[#This Row],[Customer_ID]],Customers!A:A,Customers!C:C) -> Mumbai | AB73: =TEXT(Table1[[#This Row],[Order_Date]],"mmm") -> Jun
A74: ORD00036 | B74: 46167 | C74: CUST022 | D74: REST011 | E74: DP014 | F74: 1796.62 | G74: 50 | H74: 300 | I74: 6.5 | J74: 45 | K74: 4.5 | L74: Delivered | M74: =PROPER(TRIM(L74)) -> Delivered | N74: Credit Card | O74: =TRIM(N74) -> Credit Card | P74: PREMIUM10 | Q74: =TRIM(P74) -> PREMIUM10 | R74: CMP004 | T74: =_xlfn.XLOOKUP(Table1[[#This Row],[Customer_ID]],Customers!A:A,Customers!B:B) -> Neha Shinde | U74: =_xlfn.XLOOKUP(Table1[[#This Row],[Restaurant_ID]],Restaurants!A:A,Restaurants!B:B) -> Wok Express | V74: =_xlfn.XLOOKUP(Table1[[#This Row],[Delivery_Partner_ID]],Delivery_Partners!A:A,Delivery_Partners!B:B) -> Arjun | W74: =_xlfn.XLOOKUP(Table1[[#This Row],[Campaign_ID]],Campaigns!A:A,Campaigns!B:B) -> Lunch Saver | X74: =Table1[[#This Row],[Order_Value]]+Table1[[#This Row],[Delivery_Fee]]-Table1[[#This Row],[Discount]] -> 1546.62 | Y74: {=_xlfn.IFS(Table1[[#This Row],[Delivery_Time_Min]]<=30,"On Time",Table1[[#This Row],[Delivery_Time_Min]]<=45,"At Risk",TRUE,"SLA Breach")} -> At Risk | Z74: {=_xlfn.IFS( Table1[[#This Row],[Order_Status]]="Cancelled","Critical - Cancelled", Table1[[#This Row],[Delivery SLA Status]]="SLA Breach","Critical - Late Delivery", Table1[[#This Row],[Customer_Rating]]<3,"Attention - Low Rating", TRUE,"Normal" )} -> Normal | AA74: =_xlfn.XLOOKUP(Table1[[#This Row],[Customer_ID]],Customers!A:A,Customers!C:C) -> Hyderabad | AB74: =TEXT(Table1[[#This Row],[Order_Date]],"mmm") -> May
A75: ORD00038 | B75: 46196 | C75: CUST046 | D75: REST002 | E75: DP011 | F75: 1241.42 | G75: 25 | H75: 149.49 | I75: 4.9 | J75: 28 | K75: 4.5 | L75: Delivered | M75: =PROPER(TRIM(L75)) -> Delivered | N75: Wallet | O75: =TRIM(N75) -> Wallet | P75: LUNCH15 | Q75: =TRIM(P75) -> LUNCH15 | R75: CMP001 | T75: =_xlfn.XLOOKUP(Table1[[#This Row],[Customer_ID]],Customers!A:A,Customers!B:B) -> Aditya Shinde | U75: =_xlfn.XLOOKUP(Table1[[#This Row],[Restaurant_ID]],Restaurants!A:A,Restaurants!B:B) -> Urban Tadka | V75: =_xlfn.XLOOKUP(Table1[[#This Row],[Delivery_Partner_ID]],Delivery_Partners!A:A,Delivery_Partners!B:B) -> Prakash | W75: =_xlfn.XLOOKUP(Table1[[#This Row],[Campaign_ID]],Campaigns!A:A,Campaigns!B:B) -> Weekend Feast | X75: =Table1[[#This Row],[Order_Value]]+Table1[[#This Row],[Delivery_Fee]]-Table1[[#This Row],[Discount]] -> 1116.93 | Y75: {=_xlfn.IFS(Table1[[#This Row],[Delivery_Time_Min]]<=30,"On Time",Table1[[#This Row],[Delivery_Time_Min]]<=45,"At Risk",TRUE,"SLA Breach")} -> On Time | Z75: {=_xlfn.IFS( Table1[[#This Row],[Order_Status]]="Cancelled","Critical - Cancelled", Table1[[#This Row],[Delivery SLA Status]]="SLA Breach","Critical - Late Delivery", Table1[[#This Row],[Customer_Rating]]<3,"Attention - Low Rating", TRUE,"Normal" )} -> Normal | AA75: =_xlfn.XLOOKUP(Table1[[#This Row],[Customer_ID]],Customers!A:A,Customers!C:C) -> Pune | AB75: =TEXT(Table1[[#This Row],[Order_Date]],"mmm") -> Jun
A76: ORD00040 | B76: 46186 | C76: CUST001 | D76: REST025 | E76: DP011 | F76: 565.25 | G76: 30 | H76: 100.19 | I76: 4 | J76: 29 | K76: 3 | L76: Delivered | M76: =PROPER(TRIM(L76)) -> Delivered | N76: Debit Card | O76: =TRIM(N76) -> Debit Card | P76: MONSOON20 | Q76: =TRIM(P76) -> MONSOON20 | R76: CMP008 | T76: =_xlfn.XLOOKUP(Table1[[#This Row],[Customer_ID]],Customers!A:A,Customers!B:B) -> Neha Kulkarni | U76: =_xlfn.XLOOKUP(Table1[[#This Row],[Restaurant_ID]],Restaurants!A:A,Restaurants!B:B) -> Tandoor Tales | V76: =_xlfn.XLOOKUP(Table1[[#This Row],[Delivery_Partner_ID]],Delivery_Partners!A:A,Delivery_Partners!B:B) -> Prakash | W76: =_xlfn.XLOOKUP(Table1[[#This Row],[Campaign_ID]],Campaigns!A:A,Campaigns!B:B) -> Monsoon Meals | X76: =Table1[[#This Row],[Order_Value]]+Table1[[#This Row],[Delivery_Fee]]-Table1[[#This Row],[Discount]] -> 495.06 | Y76: {=_xlfn.IFS(Table1[[#This Row],[Delivery_Time_Min]]<=30,"On Time",Table1[[#This Row],[Delivery_Time_Min]]<=45,"At Risk",TRUE,"SLA Breach")} -> On Time | Z76: {=_xlfn.IFS( Table1[[#This Row],[Order_Status]]="Cancelled","Critical - Cancelled", Table1[[#This Row],[Delivery SLA Status]]="SLA Breach","Critical - Late Delivery", Table1[[#This Row],[Customer_Rating]]<3,"Attention - Low Rating", TRUE,"Normal" )} -> Normal | AA76: =_xlfn.XLOOKUP(Table1[[#This Row],[Customer_ID]],Customers!A:A,Customers!C:C) -> Nagpur | AB76: =TEXT(Table1[[#This Row],[Order_Date]],"mmm") -> Jun
... A251: ORD00276 | B251: 46176 | C251: CUST079 | D251: REST025 | E251: DP020 | F251: 702.62 | G251: 40 | H251: 60.67 | I251: 8.2 | J251: 34 | K251: 4 | L251: Delivered | M251: =PROPER(TRIM(L251)) -> Delivered | N251: Credit Card | O251: =TRIM(N251) -> Credit Card | P251: SAVE100 | Q251: =TRIM(P251) -> SAVE100 | R251: CMP001 | T251: =_xlfn.XLOOKUP(Table1[[#This Row],[Customer_ID]],Customers!A:A,Customers!B:B) -> Aarav Sharma | U251: =_xlfn.XLOOKUP(Table1[[#This Row],[Restaurant_ID]],Restaurants!A:A,Restaurants!B:B) -> Tandoor Tales | V251: =_xlfn.XLOOKUP(Table1[[#This Row],[Delivery_Partner_ID]],Delivery_Partners!A:A,Delivery_Partners!B:B) -> Mahesh | W251: =_xlfn.XLOOKUP(Table1[[#This Row],[Campaign_ID]],Campaigns!A:A,Campaigns!B:B) -> Weekend Feast | X251: =Table1[[#This Row],[Order_Value]]+Table1[[#This Row],[Delivery_Fee]]-Table1[[#This Row],[Discount]] -> 681.95 | Y251: {=_xlfn.IFS(Table1[[#This Row],[Delivery_Time_Min]]<=30,"On Time",Table1[[#This Row],[Delivery_Time_Min]]<=45,"At Risk",TRUE,"SLA Breach")} -> At Risk | Z251: {=_xlfn.IFS( Table1[[#This Row],[Order_Status]]="Cancelled","Critical - Cancelled", Table1[[#This Row],[Delivery SLA Status]]="SLA Breach","Critical - Late Delivery", Table1[[#This Row],[Customer_Rating]]<3,"Attention - Low Rating", TRUE,"Normal" )} -> Normal | AA251: =_xlfn.XLOOKUP(Table1[[#This Row],[Customer_ID]],Customers!A:A,Customers!C:C) -> Nashik | AB251: =TEXT(Table1[[#This Row],[Order_Date]],"mmm") -> Jun
A252: ORD00277 | B252: 46201 | C252: CUST009 | D252: REST010 | E252: DP007 | F252: 1181.61 | G252: 35 | H252: 203.61 | I252: 7.4 | J252: 35 | L252: Delivered | M252: =PROPER(TRIM(L252)) -> Delivered | N252: Credit Card | O252: =TRIM(N252) -> Credit Card | P252: MONSOON20 | Q252: =TRIM(P252) -> MONSOON20 | R252: CMP004 | T252: =_xlfn.XLOOKUP(Table1[[#This Row],[Customer_ID]],Customers!A:A,Customers!B:B) -> Vivaan Kulkarni | U252: =_xlfn.XLOOKUP(Table1[[#This Row],[Restaurant_ID]],Restaurants!A:A,Restaurants!B:B) -> Dosa Junction | V252: =_xlfn.XLOOKUP(Table1[[#This Row],[Delivery_Partner_ID]],Delivery_Partners!A:A,Delivery_Partners!B:B) -> Imran | W252: =_xlfn.XLOOKUP(Table1[[#This Row],[Campaign_ID]],Campaigns!A:A,Campaigns!B:B) -> Lunch Saver | X252: =Table1[[#This Row],[Order_Value]]+Table1[[#This Row],[Delivery_Fee]]-Table1[[#This Row],[Discount]] -> 1013 | Y252: {=_xlfn.IFS(Table1[[#This Row],[Delivery_Time_Min]]<=30,"On Time",Table1[[#This Row],[Delivery_Time_Min]]<=45,"At Risk",TRUE,"SLA Breach")} -> At Risk | Z252: {=_xlfn.IFS( Table1[[#This Row],[Order_Status]]="Cancelled","Critical - Cancelled", Table1[[#This Row],[Delivery SLA Status]]="SLA Breach","Critical - Late Delivery", Table1[[#This Row],[Customer_Rating]]<3,"Attention - Low Rating", TRUE,"Normal" )} -> Attention - Low Rating | AA252: =_xlfn.XLOOKUP(Table1[[#This Row],[Customer_ID]],Customers!A:A,Customers!C:C) -> Pune | AB252: =TEXT(Table1[[#This Row],[Order_Date]],"mmm") -> Jun
A253: ORD00278 | B253: 46192 | C253: CUST002 | D253: REST002 | E253: DP017 | F253: 1540.83 | G253: 35 | H253: 300 | I253: 8.6 | J253: 42 | K253: 4.5 | L253: Delivered | M253: =PROPER(TRIM(L253)) -> Delivered | N253: UPI | O253: =TRIM(N253) -> UPI | P253: SAVE100 | Q253: =TRIM(P253) -> SAVE100 | R253: CMP008 | T253: =_xlfn.XLOOKUP(Table1[[#This Row],[Customer_ID]],Customers!A:A,Customers!B:B) -> Neha Gupta | U253: =_xlfn.XLOOKUP(Table1[[#This Row],[Restaurant_ID]],Restaurants!A:A,Restaurants!B:B) -> Urban Tadka | V253: =_xlfn.XLOOKUP(Table1[[#This Row],[Delivery_Partner_ID]],Delivery_Partners!A:A,Delivery_Partners!B:B) -> Sanjay | W253: =_xlfn.XLOOKUP(Table1[[#This Row],[Campaign_ID]],Campaigns!A:A,Campaigns!B:B) -> Monsoon Meals | X253: =Table1[[#This Row],[Order_Value]]+Table1[[#This Row],[Delivery_Fee]]-Table1[[#This Row],[Discount]] -> 1275.83 | Y253: {=_xlfn.IFS(Table1[[#This Row],[Delivery_Time_Min]]<=30,"On Time",Table1[[#This Row],[Delivery_Time_Min]]<=45,"At Risk",TRUE,"SLA Breach")} -> At Risk | Z253: {=_xlfn.IFS( Table1[[#This Row],[Order_Status]]="Cancelled","Critical - Cancelled", Table1[[#This Row],[Delivery SLA Status]]="SLA Breach","Critical - Late Delivery", Table1[[#This Row],[Customer_Rating]]<3,"Attention - Low Rating", TRUE,"Normal" )} -> Normal | AA253: =_xlfn.XLOOKUP(Table1[[#This Row],[Customer_ID]],Customers!A:A,Customers!C:C) -> Pune | AB253: =TEXT(Table1[[#This Row],[Order_Date]],"mmm") -> Jun
A254: ORD00279 | B254: 46209 | C254: CUST075 | D254: REST001 | E254: DP015 | F254: 1921.49 | G254: 35 | H254: 300 | I254: 6.6 | J254: 36 | K254: 4.5 | L254: Delivered | M254: =PROPER(TRIM(L254)) -> Delivered | N254: Debit Card | O254: =TRIM(N254) -> Debit Card | P254: MONSOON20 | Q254: =TRIM(P254) -> MONSOON20 | R254: CMP004 | T254: =_xlfn.XLOOKUP(Table1[[#This Row],[Customer_ID]],Customers!A:A,Customers!B:B) -> Rahul Jadhav | U254: =_xlfn.XLOOKUP(Table1[[#This Row],[Restaurant_ID]],Restaurants!A:A,Restaurants!B:B) -> Spice Hub | V254: =_xlfn.XLOOKUP(Table1[[#This Row],[Delivery_Partner_ID]],Delivery_Partners!A:A,Delivery_Partners!B:B) -> Vivek | W254: =_xlfn.XLOOKUP(Table1[[#This Row],[Campaign_ID]],Campaigns!A:A,Campaigns!B:B) -> Lunch Saver | X254: =Table1[[#This Row],[Order_Value]]+Table1[[#This Row],[Delivery_Fee]]-Table1[[#This Row],[Discount]] -> 1656.49 | Y254: {=_xlfn.IFS(Table1[[#This Row],[Delivery_Time_Min]]<=30,"On Time",Table1[[#This Row],[Delivery_Time_Min]]<=45,"At Risk",TRUE,"SLA Breach")} -> At Risk | Z254: {=_xlfn.IFS( Table1[[#This Row],[Order_Status]]="Cancelled","Critical - Cancelled", Table1[[#This Row],[Delivery SLA Status]]="SLA Breach","Critical - Late Delivery", Table1[[#This Row],[Customer_Rating]]<3,"Attention - Low Rating", TRUE,"Normal" )} -> Normal | AA254: =_xlfn.XLOOKUP(Table1[[#This Row],[Customer_ID]],Customers!A:A,Customers!C:C) -> Pune | AB254: =TEXT(Table1[[#This Row],[Order_Date]],"mmm") -> Jul
A255: ORD00282 | B255: 46169 | C255: CUST076 | D255: REST009 | E255: DP010 | F255: 1900.29 | G255: 25 | H255: 0 | I255: 6.3 | J255: 41 | K255: 3.5 | L255: Delivered | M255: =PROPER(TRIM(L255)) -> Delivered | N255: UPI | O255: =TRIM(N255) -> UPI | P255: NONE | Q255: =TRIM(P255) -> NONE | R255: CMP008 | T255: =_xlfn.XLOOKUP(Table1[[#This Row],[Customer_ID]],Customers!A:A,Customers!B:B) -> Vivaan Kulkarni | U255: =_xlfn.XLOOKUP(Table1[[#This Row],[Restaurant_ID]],Restaurants!A:A,Restaurants!B:B) -> Cafe Aroma | V255: =_xlfn.XLOOKUP(Table1[[#This Row],[Delivery_Partner_ID]],Delivery_Partners!A:A,Delivery_Partners!B:B) -> Nitin | W255: =_xlfn.XLOOKUP(Table1[[#This Row],[Campaign_ID]],Campaigns!A:A,Campaigns!B:B) -> Monsoon Meals | X255: =Table1[[#This Row],[Order_Value]]+Table1[[#This Row],[Delivery_Fee]]-Table1[[#This Row],[Discount]] -> 1925.29 | Y255: {=_xlfn.IFS(Table1[[#This Row],[Delivery_Time_Min]]<=30,"On Time",Table1[[#This Row],[Delivery_Time_Min]]<=45,"At Risk",TRUE,"SLA Breach")} -> At Risk | Z255: {=_xlfn.IFS( Table1[[#This Row],[Order_Status]]="Cancelled","Critical - Cancelled", Table1[[#This Row],[Delivery SLA Status]]="SLA Breach","Critical - Late Delivery", Table1[[#This Row],[Customer_Rating]]<3,"Attention - Low Rating", TRUE,"Normal" )} -> Normal | AA255: =_xlfn.XLOOKUP(Table1[[#This Row],[Customer_ID]],Customers!A:A,Customers!C:C) -> Mumbai | AB255: =TEXT(Table1[[#This Row],[Order_Date]],"mmm") -> May
A256: ORD00284 | B256: 46165 | C256: CUST045 | D256: REST004 | E256: DP014 | F256: 1231.18 | G256: 40 | H256: 0 | I256: 9.7 | J256: 51 | K256: 4.5 | L256: Delivered | M256: =PROPER(TRIM(L256)) -> Delivered | N256: Debit Card | O256: =TRIM(N256) -> Debit Card | P256: NONE | Q256: =TRIM(P256) -> NONE | R256: CMP007 | T256: =_xlfn.XLOOKUP(Table1[[#This Row],[Customer_ID]],Customers!A:A,Customers!B:B) -> Amit More | U256: =_xlfn.XLOOKUP(Table1[[#This Row],[Restaurant_ID]],Restaurants!A:A,Restaurants!B:B) -> The Food Factory | V256: =_xlfn.XLOOKUP(Table1[[#This Row],[Delivery_Partner_ID]],Delivery_Partners!A:A,Delivery_Partners!B:B) -> Arjun | W256: =_xlfn.XLOOKUP(Table1[[#This Row],[Campaign_ID]],Campaigns!A:A,Campaigns!B:B) -> First Order | X256: =Table1[[#This Row],[Order_Value]]+Table1[[#This Row],[Delivery_Fee]]-Table1[[#This Row],[Discount]] -> 1271.18 | Y256: {=_xlfn.IFS(Table1[[#This Row],[Delivery_Time_Min]]<=30,"On Time",Table1[[#This Row],[Delivery_Time_Min]]<=45,"At Risk",TRUE,"SLA Breach")} -> SLA Breach | Z256: {=_xlfn.IFS( Table1[[#This Row],[Order_Status]]="Cancelled","Critical - Cancelled", Table1[[#This Row],[Delivery SLA Status]]="SLA Breach","Critical - Late Delivery", Table1[[#This Row],[Customer_Rating]]<3,"Attention - Low Rating", TRUE,"Normal" )} -> Critical - Late Delivery | AA256: =_xlfn.XLOOKUP(Table1[[#This Row],[Customer_ID]],Customers!A:A,Customers!C:C) -> Bengaluru | AB256: =TEXT(Table1[[#This Row],[Order_Date]],"mmm") -> May
A257: ORD00285 | B257: 46157 | C257: CUST016 | D257: REST005 | E257: DP004 | F257: 1836.89 | G257: 35 | H257: 151.13 | I257: 9 | J257: 50 | K257: 3.5 | L257: Delivered | M257: =PROPER(TRIM(L257)) -> Delivered | N257: UPI | O257: =TRIM(N257) -> UPI | P257: FESTIVE25 | Q257: =TRIM(P257) -> FESTIVE25 | R257: CMP005 | T257: =_xlfn.XLOOKUP(Table1[[#This Row],[Customer_ID]],Customers!A:A,Customers!B:B) -> Aarav More | U257: =_xlfn.XLOOKUP(Table1[[#This Row],[Restaurant_ID]],Restaurants!A:A,Restaurants!B:B) -> Green Bowl | V257: =_xlfn.XLOOKUP(Table1[[#This Row],[Delivery_Partner_ID]],Delivery_Partners!A:A,Delivery_Partners!B:B) -> Vikas | W257: =_xlfn.XLOOKUP(Table1[[#This Row],[Campaign_ID]],Campaigns!A:A,Campaigns!B:B) -> Budget Bites | X257: =Table1[[#This Row],[Order_Value]]+Table1[[#This Row],[Delivery_Fee]]-Table1[[#This Row],[Discount]] -> 1720.76 | Y257: {=_xlfn.IFS(Table1[[#This Row],[Delivery_Time_Min]]<=30,"On Time",Table1[[#This Row],[Delivery_Time_Min]]<=45,"At Risk",TRUE,"SLA Breach")} -> SLA Breach | Z257: {=_xlfn.IFS( Table1[[#This Row],[Order_Status]]="Cancelled","Critical - Cancelled", Table1[[#This Row],[Delivery SLA Status]]="SLA Breach","Critical - Late Delivery", Table1[[#This Row],[Customer_Rating]]<3,"Attention - Low Rating", TRUE,"Normal" )} -> Critical - Late Delivery | AA257: =_xlfn.XLOOKUP(Table1[[#This Row],[Customer_ID]],Customers!A:A,Customers!C:C) -> Pune | AB257: =TEXT(Table1[[#This Row],[Order_Date]],"mmm") -> May
A258: ORD00286 | B258: 46159 | C258: CUST041 | D258: REST022 | E258: DP015 | F258: 654.53 | G258: 35 | H258: 89.2 | I258: 9 | J258: 39 | K258: 2.5 | L258: Delivered | M258: =PROPER(TRIM(L258)) -> Delivered | N258: Debit Card | O258: =TRIM(N258) -> Debit Card | P258: SAVE100 | Q258: =TRIM(P258) -> SAVE100 | R258: CMP004 | T258: =_xlfn.XLOOKUP(Table1[[#This Row],[Customer_ID]],Customers!A:A,Customers!B:B) -> Sakshi Gupta | U258: =_xlfn.XLOOKUP(Table1[[#This Row],[Restaurant_ID]],Restaurants!A:A,Restaurants!B:B) -> Chinese Wok | V258: =_xlfn.XLOOKUP(Table1[[#This Row],[Delivery_Partner_ID]],Delivery_Partners!A:A,Delivery_Partners!B:B) -> Vivek | W258: =_xlfn.XLOOKUP(Table1[[#This Row],[Campaign_ID]],Campaigns!A:A,Campaigns!B:B) -> Lunch Saver | X258: =Table1[[#This Row],[Order_Value]]+Table1[[#This Row],[Delivery_Fee]]-Table1[[#This Row],[Discount]] -> 600.33 | Y258: {=_xlfn.IFS(Table1[[#This Row],[Delivery_Time_Min]]<=30,"On Time",Table1[[#This Row],[Delivery_Time_Min]]<=45,"At Risk",TRUE,"SLA Breach")} -> At Risk | Z258: {=_xlfn.IFS( Table1[[#This Row],[Order_Status]]="Cancelled","Critical - Cancelled", Table1[[#This Row],[Delivery SLA Status]]="SLA Breach","Critical - Late Delivery", Table1[[#This Row],[Customer_Rating]]<3,"Attention - Low Rating", TRUE,"Normal" )} -> Attention - Low Rating | AA258: =_xlfn.XLOOKUP(Table1[[#This Row],[Customer_ID]],Customers!A:A,Customers!C:C) -> Nagpur | AB258: =TEXT(Table1[[#This Row],[Order_Date]],"mmm") -> May
A259: ORD00287 | B259: 46231 | C259: CUST054 | D259: REST023 | E259: DP008 | F259: 1289.18 | G259: 60 | H259: 195.99 | I259: 1.9 | J259: 15 | K259: 4 | L259: Delivered | M259: =PROPER(TRIM(L259)) -> Delivered | N259: UPI | O259: =TRIM(N259) -> UPI | P259: FESTIVE25 | Q259: =TRIM(P259) -> FESTIVE25 | R259: CMP005 | T259: =_xlfn.XLOOKUP(Table1[[#This Row],[Customer_ID]],Customers!A:A,Customers!B:B) -> Nikhil Joshi | U259: =_xlfn.XLOOKUP(Table1[[#This Row],[Restaurant_ID]],Restaurants!A:A,Restaurants!B:B) -> Maharashtra Kitchen | V259: =_xlfn.XLOOKUP(Table1[[#This Row],[Delivery_Partner_ID]],Delivery_Partners!A:A,Delivery_Partners!B:B) -> Sameer | W259: =_xlfn.XLOOKUP(Table1[[#This Row],[Campaign_ID]],Campaigns!A:A,Campaigns!B:B) -> Budget Bites | X259: =Table1[[#This Row],[Order_Value]]+Table1[[#This Row],[Delivery_Fee]]-Table1[[#This Row],[Discount]] -> 1153.19 | Y259: {=_xlfn.IFS(Table1[[#This Row],[Delivery_Time_Min]]<=30,"On Time",Table1[[#This Row],[Delivery_Time_Min]]<=45,"At Risk",TRUE,"SLA Breach")} -> On Time | Z259: {=_xlfn.IFS( Table1[[#This Row],[Order_Status]]="Cancelled","Critical - Cancelled", Table1[[#This Row],[Delivery SLA Status]]="SLA Breach","Critical - Late Delivery", Table1[[#This Row],[Customer_Rating]]<3,"Attention - Low Rating", TRUE,"Normal" )} -> Normal | AA259: =_xlfn.XLOOKUP(Table1[[#This Row],[Customer_ID]],Customers!A:A,Customers!C:C) -> Nagpur | AB259: =TEXT(Table1[[#This Row],[Order_Date]],"mmm") -> Jul
A260: ORD00288 | B260: 46171 | C260: CUST044 | D260: REST023 | E260: DP011 | F260: 1644.71 | G260: 35 | H260: 254.05 | I260: 10.6 | J260: 41 | K260: 4 | L260: Delivered | M260: =PROPER(TRIM(L260)) -> Delivered | N260: Wallet | O260: =TRIM(N260) -> Wallet | P260: LUNCH15 | Q260: =TRIM(P260) -> LUNCH15 | R260: CMP007 | T260: =_xlfn.XLOOKUP(Table1[[#This Row],[Customer_ID]],Customers!A:A,Customers!B:B) -> Aarav More | U260: =_xlfn.XLOOKUP(Table1[[#This Row],[Restaurant_ID]],Restaurants!A:A,Restaurants!B:B) -> Maharashtra Kitchen | V260: =_xlfn.XLOOKUP(Table1[[#This Row],[Delivery_Partner_ID]],Delivery_Partners!A:A,Delivery_Partners!B:B) -> Prakash | W260: =_xlfn.XLOOKUP(Table1[[#This Row],[Campaign_ID]],Campaigns!A:A,Campaigns!B:B) -> First Order | X260: =Table1[[#This Row],[Order_Value]]+Table1[[#This Row],[Delivery_Fee]]-Table1[[#This Row],[Discount]] -> 1425.66 | Y260: {=_xlfn.IFS(Table1[[#This Row],[Delivery_Time_Min]]<=30,"On Time",Table1[[#This Row],[Delivery_Time_Min]]<=45,"At Risk",TRUE,"SLA Breach")} -> At Risk | Z260: {=_xlfn.IFS( Table1[[#This Row],[Order_Status]]="Cancelled","Critical - Cancelled", Table1[[#This Row],[Delivery SLA Status]]="SLA Breach","Critical - Late Delivery", Table1[[#This Row],[Customer_Rating]]<3,"Attention - Low Rating", TRUE,"Normal" )} -> Normal | AA260: =_xlfn.XLOOKUP(Table1[[#This Row],[Customer_ID]],Customers!A:A,Customers!C:C) -> Nashik | AB260: =TEXT(Table1[[#This Row],[Order_Date]],"mmm") -> May
A261: ORD00289 | B261: 46233 | C261: CUST051 | D261: REST001 | E261: DP003 | F261: 1736.17 | G261: 40 | H261: 300 | I261: 8.7 | J261: 45 | K261: 5 | L261: Delivered | M261: =PROPER(TRIM(L261)) -> Delivered | N261: Debit Card | O261: =TRIM(N261) -> Debit Card | P261: FESTIVE25 | Q261: =TRIM(P261) -> FESTIVE25 | R261: CMP004 | T261: =_xlfn.XLOOKUP(Table1[[#This Row],[Customer_ID]],Customers!A:A,Customers!B:B) -> Amit Desai | U261: =_xlfn.XLOOKUP(Table1[[#This Row],[Restaurant_ID]],Restaurants!A:A,Restaurants!B:B) -> Spice Hub | V261: =_xlfn.XLOOKUP(Table1[[#This Row],[Delivery_Partner_ID]],Delivery_Partners!A:A,Delivery_Partners!B:B) -> Suresh | W261: =_xlfn.XLOOKUP(Table1[[#This Row],[Campaign_ID]],Campaigns!A:A,Campaigns!B:B) -> Lunch Saver | X261: =Table1[[#This Row],[Order_Value]]+Table1[[#This Row],[Delivery_Fee]]-Table1[[#This Row],[Discount]] -> 1476.17 | Y261: {=_xlfn.IFS(Table1[[#This Row],[Delivery_Time_Min]]<=30,"On Time",Table1[[#This Row],[Delivery_Time_Min]]<=45,"At Risk",TRUE,"SLA Breach")} -> At Risk | Z261: {=_xlfn.IFS( Table1[[#This Row],[Order_Status]]="Cancelled","Critical - Cancelled", Table1[[#This Row],[Delivery SLA Status]]="SLA Breach","Critical - Late Delivery", Table1[[#This Row],[Customer_Rating]]<3,"Attention - Low Rating", TRUE,"Normal" )} -> Normal | AA261: =_xlfn.XLOOKUP(Table1[[#This Row],[Customer_ID]],Customers!A:A,Customers!C:C) -> Nagpur | AB261: =TEXT(Table1[[#This Row],[Order_Date]],"mmm") -> Jul
A262: ORD00291 | B262: 46184 | C262: CUST012 | D262: REST015 | E262: DP014 | F262: 739.72 | G262: 35 | H262: 0 | I262: 1.5 | J262: 40 | K262: 4 | L262: Delivered | M262: =PROPER(TRIM(L262)) -> Delivered | N262: UPI | O262: =TRIM(N262) -> UPI | P262: NONE | Q262: =TRIM(P262) -> NONE | R262: CMP003 | T262: =_xlfn.XLOOKUP(Table1[[#This Row],[Customer_ID]],Customers!A:A,Customers!B:B) -> Yash Gupta | U262: =_xlfn.XLOOKUP(Table1[[#This Row],[Restaurant_ID]],Restaurants!A:A,Restaurants!B:B) -> Royal Thali | V262: =_xlfn.XLOOKUP(Table1[[#This Row],[Delivery_Partner_ID]],Delivery_Partners!A:A,Delivery_Partners!B:B) -> Arjun | W262: =_xlfn.XLOOKUP(Table1[[#This Row],[Campaign_ID]],Campaigns!A:A,Campaigns!B:B) -> Premium Treat | X262: =Table1[[#This Row],[Order_Value]]+Table1[[#This Row],[Delivery_Fee]]-Table1[[#This Row],[Discount]] -> 774.72 | Y262: {=_xlfn.IFS(Table1[[#This Row],[Delivery_Time_Min]]<=30,"On Time",Table1[[#This Row],[Delivery_Time_Min]]<=45,"At Risk",TRUE,"SLA Breach")} -> At Risk | Z262: {=_xlfn.IFS( Table1[[#This Row],[Order_Status]]="Cancelled","Critical - Cancelled", Table1[[#This Row],[Delivery SLA Status]]="SLA Breach","Critical - Late Delivery", Table1[[#This Row],[Customer_Rating]]<3,"Attention - Low Rating", TRUE,"Normal" )} -> Normal | AA262: =_xlfn.XLOOKUP(Table1[[#This Row],[Customer_ID]],Customers!A:A,Customers!C:C) -> Mumbai | AB262: =TEXT(Table1[[#This Row],[Order_Date]],"mmm") -> Jun
A263: ORD00292 | B263: 46188 | C263: CUST072 | D263: REST020 | E263: DP015 | F263: 1137.13 | G263: 40 | H263: 0 | I263: 12 | J263: 55 | K263: 5 | L263: Delivered | M263: =PROPER(TRIM(L263)) -> Delivered | N263: UPI | O263: =TRIM(N263) -> UPI | P263: NONE | Q263: =TRIM(P263) -> NONE | R263: CMP008 | T263: =_xlfn.XLOOKUP(Table1[[#This Row],[Customer_ID]],Customers!A:A,Customers!B:B) -> Sakshi Desai | U263: =_xlfn.XLOOKUP(Table1[[#This Row],[Restaurant_ID]],Restaurants!A:A,Restaurants!B:B) -> Wrap Street | V263: =_xlfn.XLOOKUP(Table1[[#This Row],[Delivery_Partner_ID]],Delivery_Partners!A:A,Delivery_Partners!B:B) -> Vivek | W263: =_xlfn.XLOOKUP(Table1[[#This Row],[Campaign_ID]],Campaigns!A:A,Campaigns!B:B) -> Monsoon Meals | X263: =Table1[[#This Row],[Order_Value]]+Table1[[#This Row],[Delivery_Fee]]-Table1[[#This Row],[Discount]] -> 1177.13 | Y263: {=_xlfn.IFS(Table1[[#This Row],[Delivery_Time_Min]]<=30,"On Time",Table1[[#This Row],[Delivery_Time_Min]]<=45,"At Risk",TRUE,"SLA Breach")} -> SLA Breach | Z263: {=_xlfn.IFS( Table1[[#This Row],[Order_Status]]="Cancelled","Critical - Cancelled", Table1[[#This Row],[Delivery SLA Status]]="SLA Breach","Critical - Late Delivery", Table1[[#This Row],[Customer_Rating]]<3,"Attention - Low Rating", TRUE,"Normal" )} -> Critical - Late Delivery | AA263: =_xlfn.XLOOKUP(Table1[[#This Row],[Customer_ID]],Customers!A:A,Customers!C:C) -> Hyderabad | AB263: =TEXT(Table1[[#This Row],[Order_Date]],"mmm") -> Jun
A264: ORD00297 | B264: 46181 | C264: CUST036 | D264: REST018 | E264: DP020 | F264: 1858 | G264: 50 | H264: 187.23 | I264: 2.9 | J264: 30 | K264: 4.5 | L264: Delivered | M264: =PROPER(TRIM(L264)) -> Delivered | N264: Credit Card | O264: =TRIM(N264) -> Credit Card | P264: FESTIVE25 | Q264: =TRIM(P264) -> FESTIVE25 | R264: CMP003 | T264: =_xlfn.XLOOKUP(Table1[[#This Row],[Customer_ID]],Customers!A:A,Customers!B:B) -> Sakshi Sharma | U264: =_xlfn.XLOOKUP(Table1[[#This Row],[Restaurant_ID]],Restaurants!A:A,Restaurants!B:B) -> South Spice | V264: =_xlfn.XLOOKUP(Table1[[#This Row],[Delivery_Partner_ID]],Delivery_Partners!A:A,Delivery_Partners!B:B) -> Mahesh | W264: =_xlfn.XLOOKUP(Table1[[#This Row],[Campaign_ID]],Campaigns!A:A,Campaigns!B:B) -> Premium Treat | X264: =Table1[[#This Row],[Order_Value]]+Table1[[#This Row],[Delivery_Fee]]-Table1[[#This Row],[Discount]] -> 1720.77 | Y264: {=_xlfn.IFS(Table1[[#This Row],[Delivery_Time_Min]]<=30,"On Time",Table1[[#This Row],[Delivery_Time_Min]]<=45,"At Risk",TRUE,"SLA Breach")} -> On Time | Z264: {=_xlfn.IFS( Table1[[#This Row],[Order_Status]]="Cancelled","Critical - Cancelled", Table1[[#This Row],[Delivery SLA Status]]="SLA Breach","Critical - Late Delivery", Table1[[#This Row],[Customer_Rating]]<3,"Attention - Low Rating", TRUE,"Normal" )} -> Normal | AA264: =_xlfn.XLOOKUP(Table1[[#This Row],[Customer_ID]],Customers!A:A,Customers!C:C) -> Pune | AB264: =TEXT(Table1[[#This Row],[Order_Date]],"mmm") -> Jun
... A267: ORD00300 | B267: 46201 | C267: CUST033 | D267: REST011 | E267: DP015 | F267: 925.55 | G267: 60 | H267: 81.11 | I267: 7.6 | J267: 37 | K267: 5 | L267: Delivered | M267: =PROPER(TRIM(L267)) -> Delivered | N267: Credit Card | O267: =TRIM(N267) -> Credit Card | P267: LUNCH15 | Q267: =TRIM(P267) -> LUNCH15 | R267: CMP002 | T267: =_xlfn.XLOOKUP(Table1[[#This Row],[Customer_ID]],Customers!A:A,Customers!B:B) -> Aarav Desai | U267: =_xlfn.XLOOKUP(Table1[[#This Row],[Restaurant_ID]],Restaurants!A:A,Restaurants!B:B) -> Wok Express | V267: =_xlfn.XLOOKUP(Table1[[#This Row],[Delivery_Partner_ID]],Delivery_Partners!A:A,Delivery_Partners!B:B) -> Vivek | W267: =_xlfn.XLOOKUP(Table1[[#This Row],[Campaign_ID]],Campaigns!A:A,Campaigns!B:B) -> New User Boost | X267: =Table1[[#This Row],[Order_Value]]+Table1[[#This Row],[Delivery_Fee]]-Table1[[#This Row],[Discount]] -> 904.44 | Y267: {=_xlfn.IFS(Table1[[#This Row],[Delivery_Time_Min]]<=30,"On Time",Table1[[#This Row],[Delivery_Time_Min]]<=45,"At Risk",TRUE,"SLA Breach")} -> At Risk | Z267: {=_xlfn.IFS( Table1[[#This Row],[Order_Status]]="Cancelled","Critical - Cancelled", Table1[[#This Row],[Delivery SLA Status]]="SLA Breach","Critical - Late Delivery", Table1[[#This Row],[Customer_Rating]]<3,"Attention - Low Rating", TRUE,"Normal" )} -> Normal | AA267: =_xlfn.XLOOKUP(Table1[[#This Row],[Customer_ID]],Customers!A:A,Customers!C:C) -> Hyderabad | AB267: =TEXT(Table1[[#This Row],[Order_Date]],"mmm") -> Jun
A268: ORD00005 | B268: 46176 | C268: CUST017 | D268: REST021 | E268: DP014 | F268: 617.89 | G268: 50 | H268: 80.41 | I268: 2.2 | J268: 32 | L268: Escalated | M268: =PROPER(TRIM(L268)) -> Escalated | N268: Debit Card | O268: =TRIM(N268) -> Debit Card | P268: FESTIVE25 | Q268: =TRIM(P268) -> FESTIVE25 | R268: CMP001 | S268: Wrong item | T268: =_xlfn.XLOOKUP(Table1[[#This Row],[Customer_ID]],Customers!A:A,Customers!B:B) -> Priya Desai | U268: =_xlfn.XLOOKUP(Table1[[#This Row],[Restaurant_ID]],Restaurants!A:A,Restaurants!B:B) -> Grill House | V268: =_xlfn.XLOOKUP(Table1[[#This Row],[Delivery_Partner_ID]],Delivery_Partners!A:A,Delivery_Partners!B:B) -> Arjun | W268: =_xlfn.XLOOKUP(Table1[[#This Row],[Campaign_ID]],Campaigns!A:A,Campaigns!B:B) -> Weekend Feast | X268: =Table1[[#This Row],[Order_Value]]+Table1[[#This Row],[Delivery_Fee]]-Table1[[#This Row],[Discount]] -> 587.48 | Y268: {=_xlfn.IFS(Table1[[#This Row],[Delivery_Time_Min]]<=30,"On Time",Table1[[#This Row],[Delivery_Time_Min]]<=45,"At Risk",TRUE,"SLA Breach")} -> At Risk | Z268: {=_xlfn.IFS( Table1[[#This Row],[Order_Status]]="Cancelled","Critical - Cancelled", Table1[[#This Row],[Delivery SLA Status]]="SLA Breach","Critical - Late Delivery", Table1[[#This Row],[Customer_Rating]]<3,"Attention - Low Rating", TRUE,"Normal" )} -> Attention - Low Rating | AA268: =_xlfn.XLOOKUP(Table1[[#This Row],[Customer_ID]],Customers!A:A,Customers!C:C) -> Hyderabad | AB268: =TEXT(Table1[[#This Row],[Order_Date]],"mmm") -> Jun
A269: ORD00009 | B269: 46164 | C269: CUST056 | D269: REST025 | E269: DP003 | F269: 2549.76 | G269: 40 | H269: 218.57 | I269: 2.9 | J269: 27 | L269: Escalated | M269: =PROPER(TRIM(L269)) -> Escalated | N269: UPI | O269: =TRIM(N269) -> UPI | P269: SAVE100 | Q269: =TRIM(P269) -> SAVE100 | R269: CMP008 | S269: Late delivery | T269: =_xlfn.XLOOKUP(Table1[[#This Row],[Customer_ID]],Customers!A:A,Customers!B:B) -> Aarav Desai | U269: =_xlfn.XLOOKUP(Table1[[#This Row],[Restaurant_ID]],Restaurants!A:A,Restaurants!B:B) -> Tandoor Tales | V269: =_xlfn.XLOOKUP(Table1[[#This Row],[Delivery_Partner_ID]],Delivery_Partners!A:A,Delivery_Partners!B:B) -> Suresh | W269: =_xlfn.XLOOKUP(Table1[[#This Row],[Campaign_ID]],Campaigns!A:A,Campaigns!B:B) -> Monsoon Meals | X269: =Table1[[#This Row],[Order_Value]]+Table1[[#This Row],[Delivery_Fee]]-Table1[[#This Row],[Discount]] -> 2371.19 | Y269: {=_xlfn.IFS(Table1[[#This Row],[Delivery_Time_Min]]<=30,"On Time",Table1[[#This Row],[Delivery_Time_Min]]<=45,"At Risk",TRUE,"SLA Breach")} -> On Time | Z269: {=_xlfn.IFS( Table1[[#This Row],[Order_Status]]="Cancelled","Critical - Cancelled", Table1[[#This Row],[Delivery SLA Status]]="SLA Breach","Critical - Late Delivery", Table1[[#This Row],[Customer_Rating]]<3,"Attention - Low Rating", TRUE,"Normal" )} -> Attention - Low Rating | AA269: =_xlfn.XLOOKUP(Table1[[#This Row],[Customer_ID]],Customers!A:A,Customers!C:C) -> Pune | AB269: =TEXT(Table1[[#This Row],[Order_Date]],"mmm") -> May
A270: ORD00012 | B270: 46186 | C270: CUST018 | D270: REST006 | E270: DP003 | F270: 800.46 | G270: 20 | H270: 100.13 | I270: 3.3 | J270: 24 | L270: Escalated | M270: =PROPER(TRIM(L270)) -> Escalated | N270: UPI | O270: =TRIM(N270) -> UPI | P270: WELCOME50 | Q270: =TRIM(P270) -> WELCOME50 | R270: CMP003 | S270: Wrong item | T270: =_xlfn.XLOOKUP(Table1[[#This Row],[Customer_ID]],Customers!A:A,Customers!B:B) -> Neha Gupta | U270: =_xlfn.XLOOKUP(Table1[[#This Row],[Restaurant_ID]],Restaurants!A:A,Restaurants!B:B) -> Mumbai Masala | V270: =_xlfn.XLOOKUP(Table1[[#This Row],[Delivery_Partner_ID]],Delivery_Partners!A:A,Delivery_Partners!B:B) -> Suresh | W270: =_xlfn.XLOOKUP(Table1[[#This Row],[Campaign_ID]],Campaigns!A:A,Campaigns!B:B) -> Premium Treat | X270: =Table1[[#This Row],[Order_Value]]+Table1[[#This Row],[Delivery_Fee]]-Table1[[#This Row],[Discount]] -> 720.33 | Y270: {=_xlfn.IFS(Table1[[#This Row],[Delivery_Time_Min]]<=30,"On Time",Table1[[#This Row],[Delivery_Time_Min]]<=45,"At Risk",TRUE,"SLA Breach")} -> On Time | Z270: {=_xlfn.IFS( Table1[[#This Row],[Order_Status]]="Cancelled","Critical - Cancelled", Table1[[#This Row],[Delivery SLA Status]]="SLA Breach","Critical - Late Delivery", Table1[[#This Row],[Customer_Rating]]<3,"Attention - Low Rating", TRUE,"Normal" )} -> Attention - Low Rating | AA270: =_xlfn.XLOOKUP(Table1[[#This Row],[Customer_ID]],Customers!A:A,Customers!C:C) -> Pune | AB270: =TEXT(Table1[[#This Row],[Order_Date]],"mmm") -> Jun
A271: ORD00019 | B271: 46146 | C271: CUST001 | D271: REST008 | E271: DP008 | F271: 882.87 | G271: 20 | H271: 171.31 | I271: 8.3 | J271: 44 | L271: Escalated | M271: =PROPER(TRIM(L271)) -> Escalated | N271: Wallet | O271: =TRIM(N271) -> Wallet | P271: SAVE100 | Q271: =TRIM(P271) -> SAVE100 | R271: CMP003 | S271: Wrong item | T271: =_xlfn.XLOOKUP(Table1[[#This Row],[Customer_ID]],Customers!A:A,Customers!B:B) -> Neha Kulkarni | U271: =_xlfn.XLOOKUP(Table1[[#This Row],[Restaurant_ID]],Restaurants!A:A,Restaurants!B:B) -> Biryani House | V271: =_xlfn.XLOOKUP(Table1[[#This Row],[Delivery_Partner_ID]],Delivery_Partners!A:A,Delivery_Partners!B:B) -> Sameer | W271: =_xlfn.XLOOKUP(Table1[[#This Row],[Campaign_ID]],Campaigns!A:A,Campaigns!B:B) -> Premium Treat | X271: =Table1[[#This Row],[Order_Value]]+Table1[[#This Row],[Delivery_Fee]]-Table1[[#This Row],[Discount]] -> 731.56 | Y271: {=_xlfn.IFS(Table1[[#This Row],[Delivery_Time_Min]]<=30,"On Time",Table1[[#This Row],[Delivery_Time_Min]]<=45,"At Risk",TRUE,"SLA Breach")} -> At Risk | Z271: {=_xlfn.IFS( Table1[[#This Row],[Order_Status]]="Cancelled","Critical - Cancelled", Table1[[#This Row],[Delivery SLA Status]]="SLA Breach","Critical - Late Delivery", Table1[[#This Row],[Customer_Rating]]<3,"Attention - Low Rating", TRUE,"Normal" )} -> Attention - Low Rating | AA271: =_xlfn.XLOOKUP(Table1[[#This Row],[Customer_ID]],Customers!A:A,Customers!C:C) -> Nagpur | AB271: =TEXT(Table1[[#This Row],[Order_Date]],"mmm") -> May
A272: ORD00037 | B272: 46234 | C272: CUST076 | D272: REST023 | E272: DP010 | F272: 1278.07 | G272: 50 | H272: 133.62 | I272: 11.1 | J272: 53 | L272: Escalated | M272: =PROPER(TRIM(L272)) -> Escalated | N272: Credit Card | O272: =TRIM(N272) -> Credit Card | P272: BUDGET50 | Q272: =TRIM(P272) -> BUDGET50 | R272: CMP006 | S272: Late delivery | T272: =_xlfn.XLOOKUP(Table1[[#This Row],[Customer_ID]],Customers!A:A,Customers!B:B) -> Vivaan Kulkarni | U272: =_xlfn.XLOOKUP(Table1[[#This Row],[Restaurant_ID]],Restaurants!A:A,Restaurants!B:B) -> Maharashtra Kitchen | V272: =_xlfn.XLOOKUP(Table1[[#This Row],[Delivery_Partner_ID]],Delivery_Partners!A:A,Delivery_Partners!B:B) -> Nitin | W272: =_xlfn.XLOOKUP(Table1[[#This Row],[Campaign_ID]],Campaigns!A:A,Campaigns!B:B) -> Festival Special | X272: =Table1[[#This Row],[Order_Value]]+Table1[[#This Row],[Delivery_Fee]]-Table1[[#This Row],[Discount]] -> 1194.45 | Y272: {=_xlfn.IFS(Table1[[#This Row],[Delivery_Time_Min]]<=30,"On Time",Table1[[#This Row],[Delivery_Time_Min]]<=45,"At Risk",TRUE,"SLA Breach")} -> SLA Breach | Z272: {=_xlfn.IFS( Table1[[#This Row],[Order_Status]]="Cancelled","Critical - Cancelled", Table1[[#This Row],[Delivery SLA Status]]="SLA Breach","Critical - Late Delivery", Table1[[#This Row],[Customer_Rating]]<3,"Attention - Low Rating", TRUE,"Normal" )} -> Critical - Late Delivery | AA272: =_xlfn.XLOOKUP(Table1[[#This Row],[Customer_ID]],Customers!A:A,Customers!C:C) -> Mumbai | AB272: =TEXT(Table1[[#This Row],[Order_Date]],"mmm") -> Jul
A273: ORD00039 | B273: 46215 | C273: CUST056 | D273: REST001 | E273: DP004 | F273: 1477.16 | G273: 20 | H273: 241.6 | I273: 4.7 | J273: 22 | L273: Escalated | M273: =PROPER(TRIM(L273)) -> Escalated | N273: UPI | O273: =TRIM(N273) -> UPI | P273: PREMIUM10 | Q273: =TRIM(P273) -> PREMIUM10 | R273: CMP007 | S273: Wrong item | T273: =_xlfn.XLOOKUP(Table1[[#This Row],[Customer_ID]],Customers!A:A,Customers!B:B) -> Aarav Desai | U273: =_xlfn.XLOOKUP(Table1[[#This Row],[Restaurant_ID]],Restaurants!A:A,Restaurants!B:B) -> Spice Hub | V273: =_xlfn.XLOOKUP(Table1[[#This Row],[Delivery_Partner_ID]],Delivery_Partners!A:A,Delivery_Partners!B:B) -> Vikas | W273: =_xlfn.XLOOKUP(Table1[[#This Row],[Campaign_ID]],Campaigns!A:A,Campaigns!B:B) -> First Order | X273: =Table1[[#This Row],[Order_Value]]+Table1[[#This Row],[Delivery_Fee]]-Table1[[#This Row],[Discount]] -> 1255.56 | Y273: {=_xlfn.IFS(Table1[[#This Row],[Delivery_Time_Min]]<=30,"On Time",Table1[[#This Row],[Delivery_Time_Min]]<=45,"At Risk",TRUE,"SLA Breach")} -> On Time | Z273: {=_xlfn.IFS( Table1[[#This Row],[Order_Status]]="Cancelled","Critical - Cancelled", Table1[[#This Row],[Delivery SLA Status]]="SLA Breach","Critical - Late Delivery", Table1[[#This Row],[Customer_Rating]]<3,"Attention - Low Rating", TRUE,"Normal" )} -> Attention - Low Rating | AA273: =_xlfn.XLOOKUP(Table1[[#This Row],[Customer_ID]],Customers!A:A,Customers!C:C) -> Pune | AB273: =TEXT(Table1[[#This Row],[Order_Date]],"mmm") -> Jul
A274: ORD00043 | B274: 46159 | C274: CUST007 | D274: REST009 | E274: DP019 | F274: 1053.48 | G274: 50 | H274: 92.37 | I274: 6 | J274: 29 | L274: Escalated | M274: =PROPER(TRIM(L274)) -> Escalated | N274: Debit Card | O274: =TRIM(N274) -> Debit Card | P274: MONSOON20 | Q274: =TRIM(P274) -> MONSOON20 | R274: CMP008 | S274: Refund issue | T274: =_xlfn.XLOOKUP(Table1[[#This Row],[Customer_ID]],Customers!A:A,Customers!B:B) -> Aditya Joshi | U274: =_xlfn.XLOOKUP(Table1[[#This Row],[Restaurant_ID]],Restaurants!A:A,Restaurants!B:B) -> Cafe Aroma | V274: =_xlfn.XLOOKUP(Table1[[#This Row],[Delivery_Partner_ID]],Delivery_Partners!A:A,Delivery_Partners!B:B) -> Ajay | W274: =_xlfn.XLOOKUP(Table1[[#This Row],[Campaign_ID]],Campaigns!A:A,Campaigns!B:B) -> Monsoon Meals | X274: =Table1[[#This Row],[Order_Value]]+Table1[[#This Row],[Delivery_Fee]]-Table1[[#This Row],[Discount]] -> 1011.11 | Y274: {=_xlfn.IFS(Table1[[#This Row],[Delivery_Time_Min]]<=30,"On Time",Table1[[#This Row],[Delivery_Time_Min]]<=45,"At Risk",TRUE,"SLA Breach")} -> On Time | Z274: {=_xlfn.IFS( Table1[[#This Row],[Order_Status]]="Cancelled","Critical - Cancelled", Table1[[#This Row],[Delivery SLA Status]]="SLA Breach","Critical - Late Delivery", Table1[[#This Row],[Customer_Rating]]<3,"Attention - Low Rating", TRUE,"Normal" )} -> Attention - Low Rating | AA274: =_xlfn.XLOOKUP(Table1[[#This Row],[Customer_ID]],Customers!A:A,Customers!C:C) -> Bengaluru | AB274: =TEXT(Table1[[#This Row],[Order_Date]],"mmm") -> May
A275: ORD00047 | B275: 46203 | C275: CUST068 | D275: REST018 | E275: DP005 | F275: 1390.94 | G275: 40 | H275: 187.54 | I275: 2.4 | J275: 27 | L275: Escalated | M275: =PROPER(TRIM(L275)) -> Escalated | N275: Debit Card | O275: =TRIM(N275) -> Debit Card | P275: SAVE100 | Q275: =TRIM(P275) -> SAVE100 | R275: CMP001 | S275: Late delivery | T275: =_xlfn.XLOOKUP(Table1[[#This Row],[Customer_ID]],Customers!A:A,Customers!B:B) -> Rahul Gupta | U275: =_xlfn.XLOOKUP(Table1[[#This Row],[Restaurant_ID]],Restaurants!A:A,Restaurants!B:B) -> South Spice | V275: =_xlfn.XLOOKUP(Table1[[#This Row],[Delivery_Partner_ID]],Delivery_Partners!A:A,Delivery_Partners!B:B) -> Ravi | W275: =_xlfn.XLOOKUP(Table1[[#This Row],[Campaign_ID]],Campaigns!A:A,Campaigns!B:B) -> Weekend Feast | X275: =Table1[[#This Row],[Order_Value]]+Table1[[#This Row],[Delivery_Fee]]-Table1[[#This Row],[Discount]] -> 1243.4 | Y275: {=_xlfn.IFS(Table1[[#This Row],[Delivery_Time_Min]]<=30,"On Time",Table1[[#This Row],[Delivery_Time_Min]]<=45,"At Risk",TRUE,"SLA Breach")} -> On Time | Z275: {=_xlfn.IFS( Table1[[#This Row],[Order_Status]]="Cancelled","Critical - Cancelled", Table1[[#This Row],[Delivery SLA Status]]="SLA Breach","Critical - Late Delivery", Table1[[#This Row],[Customer_Rating]]<3,"Attention - Low Rating", TRUE,"Normal" )} -> Attention - Low Rating | AA275: =_xlfn.XLOOKUP(Table1[[#This Row],[Customer_ID]],Customers!A:A,Customers!C:C) -> Nagpur | AB275: =TEXT(Table1[[#This Row],[Order_Date]],"mmm") -> Jun
A276: ORD00053 | B276: 46173 | C276: CUST059 | D276: REST016 | E276: DP009 | F276: 1415.29 | G276: 60 | H276: 262.37 | I276: 2.7 | J276: 35 | L276: Escalated | M276: =PROPER(TRIM(L276)) -> Escalated | N276: Credit Card | O276: =TRIM(N276) -> Credit Card | P276: FESTIVE25 | Q276: =TRIM(P276) -> FESTIVE25 | R276: CMP005 | S276: Late delivery | T276: =_xlfn.XLOOKUP(Table1[[#This Row],[Customer_ID]],Customers!A:A,Customers!B:B) -> Ananya Pawar | U276: =_xlfn.XLOOKUP(Table1[[#This Row],[Restaurant_ID]],Restaurants!A:A,Restaurants!B:B) -> Healthy Harvest | V276: =_xlfn.XLOOKUP(Table1[[#This Row],[Delivery_Partner_ID]],Delivery_Partners!A:A,Delivery_Partners!B:B) -> Akash | W276: =_xlfn.XLOOKUP(Table1[[#This Row],[Campaign_ID]],Campaigns!A:A,Campaigns!B:B) -> Budget Bites | X276: =Table1[[#This Row],[Order_Value]]+Table1[[#This Row],[Delivery_Fee]]-Table1[[#This Row],[Discount]] -> 1212.92 | Y276: {=_xlfn.IFS(Table1[[#This Row],[Delivery_Time_Min]]<=30,"On Time",Table1[[#This Row],[Delivery_Time_Min]]<=45,"At Risk",TRUE,"SLA Breach")} -> At Risk | Z276: {=_xlfn.IFS( Table1[[#This Row],[Order_Status]]="Cancelled","Critical - Cancelled", Table1[[#This Row],[Delivery SLA Status]]="SLA Breach","Critical - Late Delivery", Table1[[#This Row],[Customer_Rating]]<3,"Attention - Low Rating", TRUE,"Normal" )} -> Attention - Low Rating | AA276: =_xlfn.XLOOKUP(Table1[[#This Row],[Customer_ID]],Customers!A:A,Customers!C:C) -> Mumbai | AB276: =TEXT(Table1[[#This Row],[Order_Date]],"mmm") -> May
A277: ORD00064 | B277: 46186 | C277: CUST077 | D277: REST001 | E277: DP013 | F277: 613.04 | G277: 20 | H277: 108.54 | I277: 10 | J277: 36 | L277: Escalated | M277: =PROPER(TRIM(L277)) -> Escalated | N277: Debit Card | O277: =TRIM(N277) -> Debit Card | P277: SAVE100 | Q277: =TRIM(P277) -> SAVE100 | R277: CMP004 | S277: Refund issue | T277: =_xlfn.XLOOKUP(Table1[[#This Row],[Customer_ID]],Customers!A:A,Customers!B:B) -> Aarav More | U277: =_xlfn.XLOOKUP(Table1[[#This Row],[Restaurant_ID]],Restaurants!A:A,Restaurants!B:B) -> Spice Hub | V277: =_xlfn.XLOOKUP(Table1[[#This Row],[Delivery_Partner_ID]],Delivery_Partners!A:A,Delivery_Partners!B:B) -> Deepak | W277: =_xlfn.XLOOKUP(Table1[[#This Row],[Campaign_ID]],Campaigns!A:A,Campaigns!B:B) -> Lunch Saver | X277: =Table1[[#This Row],[Order_Value]]+Table1[[#This Row],[Delivery_Fee]]-Table1[[#This Row],[Discount]] -> 524.5 | Y277: {=_xlfn.IFS(Table1[[#This Row],[Delivery_Time_Min]]<=30,"On Time",Table1[[#This Row],[Delivery_Time_Min]]<=45,"At Risk",TRUE,"SLA Breach")} -> At Risk | Z277: {=_xlfn.IFS( Table1[[#This Row],[Order_Status]]="Cancelled","Critical - Cancelled", Table1[[#This Row],[Delivery SLA Status]]="SLA Breach","Critical - Late Delivery", Table1[[#This Row],[Customer_Rating]]<3,"Attention - Low Rating", TRUE,"Normal" )} -> Attention - Low Rating | AA277: =_xlfn.XLOOKUP(Table1[[#This Row],[Customer_ID]],Customers!A:A,Customers!C:C) -> Bengaluru | AB277: =TEXT(Table1[[#This Row],[Order_Date]],"mmm") -> Jun
A278: ORD00066 | B278: 46197 | C278: CUST022 | D278: REST003 | E278: DP009 | F278: 976.15 | G278: 50 | H278: 99.9 | I278: 10.6 | J278: 46 | L278: Escalated | M278: =PROPER(TRIM(L278)) -> Escalated | N278: Cash on Delivery | O278: =TRIM(N278) -> Cash on Delivery | P278: WEEKEND20 | Q278: =TRIM(P278) -> WEEKEND20 | R278: CMP004 | S278: Refund issue | T278: =_xlfn.XLOOKUP(Table1[[#This Row],[Customer_ID]],Customers!A:A,Customers!B:B) -> Neha Shinde | U278: =_xlfn.XLOOKUP(Table1[[#This Row],[Restaurant_ID]],Restaurants!A:A,Restaurants!B:B) -> Curry Leaf | V278: =_xlfn.XLOOKUP(Table1[[#This Row],[Delivery_Partner_ID]],Delivery_Partners!A:A,Delivery_Partners!B:B) -> Akash | W278: =_xlfn.XLOOKUP(Table1[[#This Row],[Campaign_ID]],Campaigns!A:A,Campaigns!B:B) -> Lunch Saver | X278: =Table1[[#This Row],[Order_Value]]+Table1[[#This Row],[Delivery_Fee]]-Table1[[#This Row],[Discount]] -> 926.25 | Y278: {=_xlfn.IFS(Table1[[#This Row],[Delivery_Time_Min]]<=30,"On Time",Table1[[#This Row],[Delivery_Time_Min]]<=45,"At Risk",TRUE,"SLA Breach")} -> SLA Breach | Z278: {=_xlfn.IFS( Table1[[#This Row],[Order_Status]]="Cancelled","Critical - Cancelled", Table1[[#This Row],[Delivery SLA Status]]="SLA Breach","Critical - Late Delivery", Table1[[#This Row],[Customer_Rating]]<3,"Attention - Low Rating", TRUE,"Normal" )} -> Critical - Late Delivery | AA278: =_xlfn.XLOOKUP(Table1[[#This Row],[Customer_ID]],Customers!A:A,Customers!C:C) -> Hyderabad | AB278: =TEXT(Table1[[#This Row],[Order_Date]],"mmm") -> Jun
A279: ORD00085 | B279: 46160 | C279: CUST042 | D279: REST008 | E279: DP016 | F279: 1562.46 | G279: 30 | H279: 0 | I279: 5.7 | J279: 30 | L279: Escalated | M279: =PROPER(TRIM(L279)) -> Escalated | N279: Cash on Delivery | O279: =TRIM(N279) -> Cash on Delivery | P279: NONE | Q279: =TRIM(P279) -> NONE | R279: CMP001 | S279: Late delivery | T279: =_xlfn.XLOOKUP(Table1[[#This Row],[Customer_ID]],Customers!A:A,Customers!B:B) -> Aarav Joshi | U279: =_xlfn.XLOOKUP(Table1[[#This Row],[Restaurant_ID]],Restaurants!A:A,Restaurants!B:B) -> Biryani House | V279: =_xlfn.XLOOKUP(Table1[[#This Row],[Delivery_Partner_ID]],Delivery_Partners!A:A,Delivery_Partners!B:B) -> Rohit | W279: =_xlfn.XLOOKUP(Table1[[#This Row],[Campaign_ID]],Campaigns!A:A,Campaigns!B:B) -> Weekend Feast | X279: =Table1[[#This Row],[Order_Value]]+Table1[[#This Row],[Delivery_Fee]]-Table1[[#This Row],[Discount]] -> 1592.46 | Y279: {=_xlfn.IFS(Table1[[#This Row],[Delivery_Time_Min]]<=30,"On Time",Table1[[#This Row],[Delivery_Time_Min]]<=45,"At Risk",TRUE,"SLA Breach")} -> On Time | Z279: {=_xlfn.IFS( Table1[[#This Row],[Order_Status]]="Cancelled","Critical - Cancelled", Table1[[#This Row],[Delivery SLA Status]]="SLA Breach","Critical - Late Delivery", Table1[[#This Row],[Customer_Rating]]<3,"Attention - Low Rating", TRUE,"Normal" )} -> Attention - Low Rating | AA279: =_xlfn.XLOOKUP(Table1[[#This Row],[Customer_ID]],Customers!A:A,Customers!C:C) -> Nagpur | AB279: =TEXT(Table1[[#This Row],[Order_Date]],"mmm") -> May
... A301: ORD00281 | B301: 46208 | C301: CUST047 | D301: REST005 | E301: DP016 | F301: 1546.49 | G301: 35 | H301: 0 | I301: 1.5 | J301: 21 | L301: Escalated | M301: =PROPER(TRIM(L301)) -> Escalated | N301: UPI | O301: =TRIM(N301) -> UPI | P301: NONE | Q301: =TRIM(P301) -> NONE | R301: CMP005 | S301: Late delivery | T301: =_xlfn.XLOOKUP(Table1[[#This Row],[Customer_ID]],Customers!A:A,Customers!B:B) -> Vivaan Pawar | U301: =_xlfn.XLOOKUP(Table1[[#This Row],[Restaurant_ID]],Restaurants!A:A,Restaurants!B:B) -> Green Bowl | V301: =_xlfn.XLOOKUP(Table1[[#This Row],[Delivery_Partner_ID]],Delivery_Partners!A:A,Delivery_Partners!B:B) -> Rohit | W301: =_xlfn.XLOOKUP(Table1[[#This Row],[Campaign_ID]],Campaigns!A:A,Campaigns!B:B) -> Budget Bites | X301: =Table1[[#This Row],[Order_Value]]+Table1[[#This Row],[Delivery_Fee]]-Table1[[#This Row],[Discount]] -> 1581.49 | Y301: {=_xlfn.IFS(Table1[[#This Row],[Delivery_Time_Min]]<=30,"On Time",Table1[[#This Row],[Delivery_Time_Min]]<=45,"At Risk",TRUE,"SLA Breach")} -> On Time | Z301: {=_xlfn.IFS( Table1[[#This Row],[Order_Status]]="Cancelled","Critical - Cancelled", Table1[[#This Row],[Delivery SLA Status]]="SLA Breach","Critical - Late Delivery", Table1[[#This Row],[Customer_Rating]]<3,"Attention - Low Rating", TRUE,"Normal" )} -> Attention - Low Rating | AA301: =_xlfn.XLOOKUP(Table1[[#This Row],[Customer_ID]],Customers!A:A,Customers!C:C) -> Mumbai | AB301: =TEXT(Table1[[#This Row],[Order_Date]],"mmm") -> Jul

Sheet customer wise pivot
B2: City-wise Customer | F2: Customer Segment | I2: Signup Year Pivot | M2: City + Segment Analysis
A3: Row Labels | B3: Count of Customer_ID
A4: Bengaluru | B4: 15 | E4: Row Labels | F4: Count of Customer_ID
A5: Hyderabad | B5: 11 | E5: Budget | F5: 11 | H5: Row Labels | I5: Count of Customer_ID | L5: Count of Customer_ID | M5: Column Labels
A6: Mumbai | B6: 17 | E6: New | F6: 15 | H6: 2025 | I6: 43 | L6: Row Labels | M6: Budget | N6: New | O6: Premium | P6: Regular | Q6: Grand Total
A7: Nagpur | B7: 12 | E7: Premium | F7: 12 | H7: 2026 | I7: 37 | L7: Bengaluru | M7: 1 | N7: 1 | O7: 5 | P7: 8 | Q7: 15
A8: Nashik | B8: 7 | E8: Regular | F8: 42 | H8: Grand Total | I8: 80 | L8: Hyderabad | M8: 2 | O8: 3 | P8: 6 | Q8: 11
A9: Pune | B9: 18 | E9: Grand Total | F9: 80 | L9: Mumbai | M9: 2 | N9: 6 | O9: 2 | P9: 7 | Q9: 17
A10: Grand Total | B10: 80 | L10: Nagpur | M10: 3 | N10: 1 | P10: 8 | Q10: 12
L11: Nashik | M11: 1 | N11: 2 | P11: 4 | Q11: 7
L12: Pune | M12: 2 | N12: 5 | O12: 2 | P12: 9 | Q12: 18
L13: Grand Total | M13: 11 | N13: 15 | O13: 12 | P13: 42 | Q13: 80

Sheet Customers
A1: Customer_ID | B1: Customer_Name | C1: City | D1: Segment | E1: Signup_Date
A2: CUST001 | B2: Neha Kulkarni | C2: Nagpur | D2: Budget | E2: 45678
A3: CUST002 | B3: Neha Gupta | C3: Pune | D3: Premium | E3: 45745
A4: CUST003 | B4: Rohan More | C4: Hyderabad | D4: Premium | E4: 46001
A5: CUST004 | B5: Isha Pawar | C5: Pune | D5: New | E5: 45818
A6: CUST005 | B6: Isha Gupta | C6: Bengaluru | D6: Regular | E6: 46218
A7: CUST006 | B7: Pooja Desai | C7: Mumbai | D7: New | E7: 46162
A8: CUST007 | B8: Aditya Joshi | C8: Bengaluru | D8: Premium | E8: 45824
A9: CUST008 | B9: Yash Kulkarni | C9: Nagpur | D9: Regular | E9: 46003
A10: CUST009 | B10: Vivaan Kulkarni | C10: Pune | D10: Regular | E10: 46085
A11: CUST010 | B11: Priya Desai | C11: Nagpur | D11: Regular | E11: 46045
A12: CUST011 | B12: Vivaan Pawar | C12: Pune | D12: Regular | E12: 46134
A13: CUST012 | B13: Yash Gupta | C13: Mumbai | D13: Regular | E13: 45927
... A81: CUST080 | B81: Aditya Sharma | C81: Nagpur | D81: New | E81: 46213

Sheet Restaurant wise pivot
B2: Restaurant City | F2: Restaurant Rating | I2: Cuisine-wise Restaurant | M2: Restaurants-wise-rating
A3: Row Labels | B3: Count of Restaurant_ID
A4: Bengaluru | B4: 5 | E4: Row Labels | F4: Average of Restaurant_Rating
A5: Hyderabad | B5: 3 | E5: Biryani House | F5: 4.1 | I5: Row Labels | J5: Count of Restaurant_ID | M5: Row Labels | N5: Average of Commission_Rate
A6: Mumbai | B6: 3 | E6: Burger Garage | F6: 4 | I6: Burger | J6: 1 | M6: Biryani House | N6: 0.15
A7: Nagpur | B7: 2 | E7: Cafe Aroma | F7: 4.4 | I7: Chinese | J7: 2 | M7: Burger Garage | N7: 0.13
A8: Nashik | B8: 8 | E8: Chinese Wok | F8: 3.8 | I8: Desserts | J8: 1 | M8: Cafe Aroma | N8: 0.15
A9: Pune | B9: 4 | E9: Curry Leaf | F9: 3.7 | I9: Healthy | J9: 3 | M9: Chinese Wok | N9: 0.22
A10: Grand Total | B10: 25 | E10: Dosa Junction | F10: 4 | I10: Indian | J10: 3 | M10: Curry Leaf | N10: 0.13
E11: Green Bowl | F11: 4.5 | I11: Maharashtrian | J11: 3 | M11: Dosa Junction | N11: 0.22
E12: Grill House | F12: 4 | I12: North Indian | J12: 4 | M12: Green Bowl | N12: 0.15
E13: Healthy Harvest | F13: 4.7 | I13: Pizza | J13: 5 | M13: Grill House | N13: 0.15
E14: Kebab Nation | F14: 4.6 | I14: South Indian | J14: 3 | M14: Healthy Harvest | N14: 0.24
E15: Maharashtra Kitchen | F15: 4.1 | I15: Grand Total | J15: 25 | M15: Kebab Nation | N15: 0.16
E16: Mumbai Masala | F16: 4.1 | M16: Maharashtra Kitchen | N16: 0.16
E17: Pasta Point | F17: 3.8 | M17: Mumbai Masala | N17: 0.19
E18: Pizza Craft | F18: 3.3 | M18: Pasta Point | N18: 0.2
E19: Pune Bites | F19: 3.8 | M19: Pizza Craft | N19: 0.16
E20: Royal Thali | F20: 4.7 | M20: Pune Bites | N20: 0.21
E21: South Spice | F21: 4.3 | M21: Royal Thali | N21: 0.21
E22: Spice Hub | F22: 3.4 | M22: South Spice | N22: 0.22
E23: Sweet Truth | F23: 4.2 | M23: Spice Hub | N23: 0.2
E24: Tandoor Tales | F24: 4 | M24: Sweet Truth | N24: 0.19
E25: The Breakfast Club | F25: 4.5 | M25: Tandoor Tales | N25: 0.12
E26: The Food Factory | F26: 4.2 | M26: The Breakfast Club | N26: 0.17
E27: Urban Tadka | F27: 3.7 | M27: The Food Factory | N27: 0.23
... E30: Grand Total | F30: 4.092 | M30: Wrap Street | N30: 0.23
M31: Grand Total | N31: 0.1832

Sheet Restaurants
A1: Restaurant_ID | B1: Restaurant_Name | C1: Cuisine | D1: City | E1: Restaurant_Rating | F1: Commission_Rate
A2: REST001 | B2: Spice Hub | C2: North Indian | D2: Nashik | E2: 3.4 | F2: 0.2
A3: REST002 | B3: Urban Tadka | C3: Indian | D3: Mumbai | E3: 3.7 | F3: 0.22
A4: REST003 | B4: Curry Leaf | C4: North Indian | D4: Bengaluru | E4: 3.7 | F4: 0.13
A5: REST004 | B5: The Food Factory | C5: Pizza | D5: Mumbai | E5: 4.2 | F5: 0.23
A6: REST005 | B6: Green Bowl | C6: Chinese | D6: Pune | E6: 4.5 | F6: 0.15
A7: REST006 | B7: Mumbai Masala | C7: Pizza | D7: Pune | E7: 4.1 | F7: 0.19
A8: REST007 | B8: Pune Bites | C8: South Indian | D8: Hyderabad | E8: 3.8 | F8: 0.21
A9: REST008 | B9: Biryani House | C9: Maharashtrian | D9: Nagpur | E9: 4.1 | F9: 0.15
A10: REST009 | B10: Cafe Aroma | C10: Healthy | D10: Nashik | E10: 4.4 | F10: 0.15
A11: REST010 | B11: Dosa Junction | C11: Indian | D11: Pune | E11: 4 | F11: 0.22
A12: REST011 | B12: Wok Express | C12: Burger | D12: Nashik | E12: 4.6 | F12: 0.17
A13: REST012 | B13: Pizza Craft | C13: Desserts | D13: Bengaluru | E13: 3.3 | F13: 0.16
... A26: REST025 | B26: Tandoor Tales | C26: South Indian | D26: Nagpur | E26: 4 | F26: 0.12

Sheet Delivery_Partners pivote
B1: Delivery_Partners | E1: Partner Joining Year | I1: Partner Name + Vehicle Type
A3: Row Labels | B3: Count of Partner_ID
A4: Bike | B4: 10 | E4: Row Labels | F4: Count of Partner_ID
A5: Scooter | B5: 10 | E5: 2024 | F5: 11 | I5: Count of Partner_ID | J5: Column Labels
A6: Grand Total | B6: 20 | E6: 2025 | F6: 9 | I6: Row Labels | J6: Bike | K6: Scooter | L6: Grand Total
E7: Grand Total | F7: 20 | I7: Ajay | J7: 1 | L7: 1
I8: Akash | J8: 1 | L8: 1
I9: Amit | K9: 1 | L9: 1
I10: Anil | J10: 1 | L10: 1
I11: Arjun | J11: 1 | L11: 1
I12: Deepak | K12: 1 | L12: 1
I13: Imran | K13: 1 | L13: 1
I14: Kunal | J14: 1 | L14: 1
I15: Mahesh | J15: 1 | L15: 1
I16: Manoj | K16: 1 | L16: 1
I17: Nitin | K17: 1 | L17: 1
I18: Prakash | K18: 1 | L18: 1
I19: Rahul | K19: 1 | L19: 1
I20: Ravi | J20: 1 | L20: 1
I21: Rohit | J21: 1 | L21: 1
I22: Sameer | J22: 1 | L22: 1
I23: Sanjay | K23: 1 | L23: 1
I24: Suresh | K24: 1 | L24: 1
I25: Vikas | J25: 1 | L25: 1
I26: Vivek | K26: 1 | L26: 1
I27: Grand Total | J27: 10 | K27: 10 | L27: 20

Sheet Delivery_Partners
A1: Partner_ID | B1: Partner_Name | C1: Vehicle_Type | D1: Joining_Date
A2: DP001 | B2: Rahul | C2: Scooter | D2: 45929
A3: DP002 | B3: Amit | C3: Scooter | D3: 45951
A4: DP003 | B4: Suresh | C4: Scooter | D4: 45747
A5: DP004 | B5: Vikas | C5: Bike | D5: 45652
A6: DP005 | B6: Ravi | C6: Bike | D6: 45292
A7: DP006 | B7: Kunal | C7: Bike | D7: 45639
A8: DP007 | B8: Imran | C8: Scooter | D8: 45796
A9: DP008 | B9: Sameer | C9: Bike | D9: 45799
A10: DP009 | B10: Akash | C10: Bike | D10: 45700
A11: DP010 | B11: Nitin | C11: Scooter | D11: 45408
A12: DP011 | B12: Prakash | C12: Scooter | D12: 45349
A13: DP012 | B13: Manoj | C13: Scooter | D13: 45976
... A21: DP020 | B21: Mahesh | C21: Bike | D21: 45524

Sheet Campaigns wise pivote
B1: customer segment campaigns | F1: Campaign Type Analysis
A3: Row Labels | B3: Count of Campaign_ID
A4: All | B4: 3 | E4: Row Labels | F4: Count of Campaign_ID
A5: Budget | B5: 1 | E5: Flat | F5: 3
A6: New | B6: 2 | E6: Percentage | F6: 5
A7: Premium | B7: 1 | E7: Grand Total | F7: 8
A8: Regular | B8: 1
A9: Grand Total | B9: 8

Sheet Campaigns
A1: Campaign_ID | B1: Campaign_Name | C1: Discount_Type | D1: Target_Segment
A2: CMP001 | B2: Weekend Feast | C2: Percentage | D2: All
A3: CMP002 | B3: New User Boost | C3: Percentage | D3: New
A4: CMP003 | B4: Premium Treat | C4: Flat | D4: Premium
A5: CMP004 | B5: Lunch Saver | C5: Percentage | D5: Regular
A6: CMP005 | B6: Budget Bites | C6: Flat | D6: Budget
A7: CMP006 | B7: Festival Special | C7: Percentage | D7: All
A8: CMP007 | B8: First Order | C8: Flat | D8: New
A9: CMP008 | B9: Monsoon Meals | C9: Percentage | D9: All

Sheet Data_Dictionary
A1: Sheet | B1: Column | C1: Purpose
A2: Raw_Orders | B2: Customer_ID | C2: Use XLOOKUP to bring customer details
A3: Raw_Orders | B3: Restaurant_ID | C3: Use XLOOKUP to bring restaurant details
A4: Raw_Orders | B4: Delivery_Partner_ID | C4: Use XLOOKUP to bring partner details
A5: Raw_Orders | B5: Order_Value | C5: Order value before delivery fee/discount
A6: Raw_Orders | B6: Delivery_Fee | C6: Fee charged to customer
A7: Raw_Orders | B7: Discount | C7: Discount applied
A8: Raw_Orders | B8: Delivery_Time_Min | C8: Actual delivery time
A9: Raw_Orders | B9: Customer_Rating | C9: Customer rating
A10: Raw_Orders | B10: Order_Status | C10: Delivered / Cancelled / Escalated
A11: Customers | B11: Customer_ID | C11: Lookup key
A12: Customers | B12: City | C12: Customer city
... A20: Campaigns | B20: Target_Segment | C20: Campaign target
